{"meta":{"window_min":30,"latest":"2026-07-10 13:13","n":497},"commentary":["直近30分の売買代金は全体で 6847.5億円。最も資金が寄っているのは「話題・噂」層で全体の 49%。","エービーシー・マート（小売業）: 集中度 8.0x。本セッションで売買代金が集中。","ＤＭＧ森精機（機械）: 集中度 5.3x。本セッションで売買代金が集中。","オークマ（機械）: 集中度 5.2x。本セッションで売買代金が集中。","業種では「化学」に資金が広がっている（30銘柄が平常比プラス: 日本ペイントホールディングス・ユニ・チャーム・コーセーホールディングス・アイカ工業）。","シェア急伸: 安川電機 +0.34pp / ファーストリテイリング +0.31pp。","空売り残高報告: ダイキン工業に大口ショート 1件・合計 3.92%（2026-07-09公表・発行済株式数0.5%以上の報告のみ）。","空売り残高報告: ソシオネクストに大口ショート 3件・合計 3.32%（2026-07-09公表・発行済株式数0.5%以上の報告のみ）。","空売り残高報告: 日本郵船に大口ショート 2件・合計 1.81%（2026-07-06公表・発行済株式数0.5%以上の報告のみ）。","※空売り残高報告は発行済株式数0.5%以上を報告した大口投資家のみが対象(JPX公式・日次)。掲載が無い銘柄は「空売りが無い」のではなく「大口報告が無い(基準未満または未報告)」ことを意味する。信用取引残高・空売り比率(市場全体集計)はJPX公式配信がPDFのみで自動取得できないため未収録。きっかけ（ニュース等）も本データには含まれず未検証。反転/ショートスクイーズ発生の断定は行わない。投資助言ではない。"],"rows":[{"code":"2670.T","name":"エービーシー・マート","bucket":"core","sector":"小売業","surge":7.958,"z":3.2,"recent":1187609650,"share_recent":0.173,"share_base":0.026,"share_delta":0.148,"last":2592.0,"pct":-8.25},{"code":"6141.T","name":"ＤＭＧ森精機","bucket":"core","sector":"機械","surge":5.281,"z":4.8,"recent":1047441500,"share_recent":0.153,"share_base":0.026,"share_delta":0.127,"last":3680.0,"pct":2.11},{"code":"6103.T","name":"オークマ","bucket":"leader","sector":"機械","surge":5.192,"z":9.56,"recent":736679500,"share_recent":0.108,"share_base":0.015,"share_delta":0.092,"last":4850.0,"pct":1.25},{"code":"5901.T","name":"東洋製罐グループホールディングス","bucket":"core","sector":"金属製品","surge":5.054,"z":7.51,"recent":181115800,"share_recent":0.026,"share_base":0.004,"share_delta":0.023,"last":4026.0,"pct":-2.85},{"code":"3391.T","name":"ツルハホールディングス","bucket":"core","sector":"小売業","surge":4.987,"z":2.25,"recent":1547906600,"share_recent":0.226,"share_base":0.045,"share_delta":0.181,"last":2378.0,"pct":10.58},{"code":"7649.T","name":"スギホールディングス","bucket":"core","sector":"小売業","surge":4.923,"z":4.35,"recent":501577700,"share_recent":0.073,"share_base":0.013,"share_delta":0.06,"last":3174.0,"pct":-0.35},{"code":"4612.T","name":"日本ペイントホールディングス","bucket":"core","sector":"化学","surge":4.443,"z":4.36,"recent":585054750,"share_recent":0.085,"share_base":0.016,"share_delta":0.069,"last":1079.0,"pct":-0.55},{"code":"9861.T","name":"吉野家ホールディングス","bucket":"core","sector":"小売業","surge":4.439,"z":1.4,"recent":422104300,"share_recent":0.062,"share_base":0.015,"share_delta":0.047,"last":3374.0,"pct":6.91},{"code":"7282.T","name":"豊田合成","bucket":"core","sector":"輸送用機器","surge":4.426,"z":6.71,"recent":454539400,"share_recent":0.066,"share_base":0.012,"share_delta":0.055,"last":5109.0,"pct":-0.14},{"code":"1911.T","name":"住友林業","bucket":"core","sector":"建設業","surge":4.424,"z":4.01,"recent":1016957450,"share_recent":0.149,"share_base":0.029,"share_delta":0.119,"last":1312.5,"pct":-3.67},{"code":"8570.T","name":"イオンフィナンシャルサービス","bucket":"core","sector":"その他金融業","surge":4.254,"z":3.0,"recent":163435400,"share_recent":0.024,"share_base":0.005,"share_delta":0.019,"last":1525.5,"pct":1.53},{"code":"2809.T","name":"キユーピー","bucket":"core","sector":"食料品","surge":4.152,"z":4.6,"recent":465032700,"share_recent":0.068,"share_base":0.012,"share_delta":0.056,"last":4467.0,"pct":0.95},{"code":"6134.T","name":"ＦＵＪＩ","bucket":"core","sector":"機械","surge":4.084,"z":3.99,"recent":1565597300,"share_recent":0.229,"share_base":0.047,"share_delta":0.181,"last":7759.0,"pct":-5.08},{"code":"6113.T","name":"アマダ","bucket":"leader","sector":"機械","surge":3.799,"z":7.32,"recent":1649693000,"share_recent":0.241,"share_base":0.047,"share_delta":0.194,"last":2979.0,"pct":0.13},{"code":"2897.T","name":"日清食品ホールディングス","bucket":"core","sector":"食料品","surge":3.712,"z":2.54,"recent":569951800,"share_recent":0.083,"share_base":0.019,"share_delta":0.064,"last":2890.5,"pct":-0.36},{"code":"6845.T","name":"アズビル","bucket":"core","sector":"電気機器","surge":3.609,"z":1.09,"recent":319072400,"share_recent":0.047,"share_base":0.014,"share_delta":0.033,"last":1687.0,"pct":-1.14},{"code":"9532.T","name":"大阪瓦斯","bucket":"leader","sector":"電気・ガス業","surge":3.565,"z":3.94,"recent":649543000,"share_recent":0.095,"share_base":0.021,"share_delta":0.074,"last":5364.0,"pct":-0.8},{"code":"3941.T","name":"レンゴー","bucket":"core","sector":"パルプ・紙","surge":3.265,"z":2.78,"recent":190383500,"share_recent":0.028,"share_base":0.007,"share_delta":0.021,"last":1410.0,"pct":-0.28},{"code":"9024.T","name":"西武ホールディングス","bucket":"core","sector":"陸運業","surge":3.265,"z":3.27,"recent":1160348500,"share_recent":0.169,"share_base":0.041,"share_delta":0.128,"last":3473.0,"pct":3.03},{"code":"9023.T","name":"東京地下鉄","bucket":"core","sector":"陸運業","surge":3.225,"z":2.52,"recent":565294950,"share_recent":0.083,"share_base":0.022,"share_delta":0.061,"last":1444.0,"pct":-2.76},{"code":"4516.T","name":"日本新薬","bucket":"core","sector":"医薬品","surge":3.202,"z":1.28,"recent":112377000,"share_recent":0.016,"share_base":0.005,"share_delta":0.012,"last":4089.0,"pct":-1.59},{"code":"3769.T","name":"ＧＭＯペイメントゲートウェイ","bucket":"core","sector":"情報・通信業","surge":3.192,"z":5.26,"recent":553498400,"share_recent":0.081,"share_base":0.017,"share_delta":0.064,"last":9582.0,"pct":-0.43},{"code":"6586.T","name":"マキタ","bucket":"core","sector":"機械","surge":3.181,"z":0.83,"recent":620023700,"share_recent":0.091,"share_base":0.028,"share_delta":0.063,"last":5600.0,"pct":-3.88},{"code":"6136.T","name":"オーエスジー","bucket":"core","sector":"機械","surge":3.157,"z":1.66,"recent":459913000,"share_recent":0.067,"share_base":0.019,"share_delta":0.048,"last":3814.0,"pct":0.26},{"code":"9735.T","name":"セコム","bucket":"leader","sector":"サービス業","surge":3.139,"z":3.82,"recent":1193597500,"share_recent":0.174,"share_base":0.043,"share_delta":0.131,"last":6708.0,"pct":0.96},{"code":"6869.T","name":"シスメックス","bucket":"core","sector":"電気機器","surge":3.137,"z":2.84,"recent":722689450,"share_recent":0.106,"share_base":0.027,"share_delta":0.079,"last":1505.5,"pct":-3.09},{"code":"6481.T","name":"ＴＨＫ","bucket":"core","sector":"機械","surge":3.102,"z":2.55,"recent":1105529400,"share_recent":0.161,"share_base":0.044,"share_delta":0.118,"last":7386.0,"pct":1.71},{"code":"3382.T","name":"セブン＆アイ・ホールディングス","bucket":"leader","sector":"小売業","surge":3.088,"z":3.97,"recent":2349212250,"share_recent":0.343,"share_base":0.081,"share_delta":0.262,"last":2033.0,"pct":-0.76},{"code":"9021.T","name":"西日本旅客鉄道","bucket":"leader","sector":"陸運業","surge":3.075,"z":3.11,"recent":1531946850,"share_recent":0.224,"share_base":0.057,"share_delta":0.167,"last":2895.5,"pct":4.15},{"code":"8111.T","name":"ゴールドウイン","bucket":"core","sector":"繊維製品","surge":3.022,"z":2.43,"recent":144914800,"share_recent":0.021,"share_base":0.005,"share_delta":0.016,"last":2249.0,"pct":-0.27},{"code":"1942.T","name":"関電工","bucket":"core","sector":"建設業","surge":2.878,"z":2.48,"recent":777906300,"share_recent":0.114,"share_base":0.032,"share_delta":0.082,"last":6380.0,"pct":-4.56},{"code":"7951.T","name":"ヤマハ","bucket":"leader","sector":"その他製品","surge":2.847,"z":2.62,"recent":247723250,"share_recent":0.036,"share_base":0.01,"share_delta":0.026,"last":1163.5,"pct":-0.04},{"code":"9706.T","name":"日本空港ビルデング","bucket":"core","sector":"不動産業","surge":2.823,"z":4.29,"recent":265409700,"share_recent":0.039,"share_base":0.01,"share_delta":0.029,"last":5257.0,"pct":1.29},{"code":"2579.T","name":"コカ・コーラ　ボトラーズジャパンホールディングス","bucket":"core","sector":"食料品","surge":2.816,"z":4.8,"recent":675734500,"share_recent":0.099,"share_base":0.024,"share_delta":0.075,"last":4171.0,"pct":-6.16},{"code":"2587.T","name":"サントリービバレッジ＆フード","bucket":"core","sector":"食料品","surge":2.806,"z":2.71,"recent":507273400,"share_recent":0.074,"share_base":0.021,"share_delta":0.053,"last":4607.0,"pct":-0.3},{"code":"3774.T","name":"インターネットイニシアティブ","bucket":"core","sector":"情報・通信業","surge":2.768,"z":2.03,"recent":275311500,"share_recent":0.04,"share_base":0.012,"share_delta":0.028,"last":3502.0,"pct":4.16},{"code":"9843.T","name":"ニトリホールディングス","bucket":"leader","sector":"小売業","surge":2.752,"z":2.09,"recent":969564000,"share_recent":0.142,"share_base":0.041,"share_delta":0.101,"last":2432.0,"pct":0.37},{"code":"5711.T","name":"三菱マテリアル","bucket":"leader","sector":"非鉄金属","surge":2.73,"z":0.71,"recent":764708200,"share_recent":0.112,"share_base":0.043,"share_delta":0.069,"last":3960.0,"pct":-12.35},{"code":"1860.T","name":"戸田建設","bucket":"core","sector":"建設業","surge":2.721,"z":3.21,"recent":192977450,"share_recent":0.028,"share_base":0.008,"share_delta":0.021,"last":1588.5,"pct":-1.73},{"code":"8283.T","name":"ＰＡＬＴＡＣ","bucket":"core","sector":"卸売業","surge":2.698,"z":0.89,"recent":93180900,"share_recent":0.014,"share_base":0.005,"share_delta":0.009,"last":6658.0,"pct":0.12},{"code":"8113.T","name":"ユニ・チャーム","bucket":"core","sector":"化学","surge":2.654,"z":2.65,"recent":458250420,"share_recent":0.067,"share_base":0.019,"share_delta":0.048,"last":957.7999877929688,"pct":-1.04},{"code":"5393.T","name":"ニチアス","bucket":"core","sector":"ガラス・土石製品","surge":2.615,"z":3.42,"recent":287275900,"share_recent":0.042,"share_base":0.011,"share_delta":0.03,"last":3707.0,"pct":-3.94},{"code":"9065.T","name":"山九","bucket":"core","sector":"陸運業","surge":2.61,"z":2.86,"recent":220375200,"share_recent":0.032,"share_base":0.009,"share_delta":0.023,"last":8756.0,"pct":0.67},{"code":"1721.T","name":"コムシスホールディングス","bucket":"leader","sector":"建設業","surge":2.546,"z":4.56,"recent":370667300,"share_recent":0.054,"share_base":0.015,"share_delta":0.04,"last":5362.0,"pct":-3.63},{"code":"6273.T","name":"ＳＭＣ","bucket":"leader","sector":"機械","surge":2.54,"z":1.53,"recent":2865547000,"share_recent":0.418,"share_base":0.14,"share_delta":0.278,"last":72210.0,"pct":-0.96},{"code":"6323.T","name":"ローツェ","bucket":"core","sector":"機械","surge":2.522,"z":2.46,"recent":1644619500,"share_recent":0.24,"share_base":0.072,"share_delta":0.168,"last":4559.0,"pct":3.64},{"code":"1417.T","name":"ミライト・ワン","bucket":"core","sector":"建設業","surge":2.519,"z":2.67,"recent":124518200,"share_recent":0.018,"share_base":0.005,"share_delta":0.013,"last":3739.0,"pct":-4.15},{"code":"5233.T","name":"太平洋セメント","bucket":"leader","sector":"ガラス・土石製品","surge":2.484,"z":2.58,"recent":260463100,"share_recent":0.038,"share_base":0.012,"share_delta":0.026,"last":3945.0,"pct":-2.11},{"code":"5947.T","name":"リンナイ","bucket":"core","sector":"金属製品","surge":2.456,"z":1.54,"recent":115783500,"share_recent":0.017,"share_base":0.006,"share_delta":0.011,"last":3569.0,"pct":-1.22},{"code":"9616.T","name":"共立メンテナンス","bucket":"core","sector":"サービス業","surge":2.408,"z":2.03,"recent":478675950,"share_recent":0.07,"share_base":0.022,"share_delta":0.048,"last":2923.5,"pct":-4.18},{"code":"8593.T","name":"三菱ＨＣキャピタル","bucket":"core","sector":"その他金融業","surge":2.402,"z":2.3,"recent":678494500,"share_recent":0.099,"share_base":0.031,"share_delta":0.068,"last":1369.0,"pct":1.03},{"code":"9435.T","name":"光通信","bucket":"core","sector":"情報・通信業","surge":2.398,"z":0.39,"recent":400746000,"share_recent":0.059,"share_base":0.024,"share_delta":0.034,"last":37210.0,"pct":5.74},{"code":"7832.T","name":"バンダイナムコホールディングス","bucket":"leader","sector":"その他製品","surge":2.393,"z":2.01,"recent":971081100,"share_recent":0.142,"share_base":0.045,"share_delta":0.097,"last":4045.0,"pct":2.04},{"code":"9533.T","name":"東邦瓦斯","bucket":"core","sector":"電気・ガス業","surge":2.382,"z":1.5,"recent":72429750,"share_recent":0.011,"share_base":0.004,"share_delta":0.007,"last":1222.0,"pct":-1.57},{"code":"8601.T","name":"大和証券グループ本社","bucket":"leader","sector":"証券、商品先物取引業","surge":2.373,"z":1.54,"recent":830567600,"share_recent":0.121,"share_base":0.044,"share_delta":0.077,"last":1728.5,"pct":3.91},{"code":"9501.T","name":"東京電力ホールディングス","bucket":"leader","sector":"電気・ガス業","surge":2.37,"z":1.48,"recent":2099561261,"share_recent":0.307,"share_base":0.109,"share_delta":0.197,"last":481.70001220703125,"pct":2.6},{"code":"4732.T","name":"ユー・エス・エス","bucket":"core","sector":"サービス業","surge":2.369,"z":0.94,"recent":259938200,"share_recent":0.038,"share_base":0.013,"share_delta":0.025,"last":2006.5,"pct":3.32},{"code":"4922.T","name":"コーセーホールディングス","bucket":"core","sector":"化学","surge":2.367,"z":2.02,"recent":189127000,"share_recent":0.028,"share_base":0.009,"share_delta":0.019,"last":5216.0,"pct":-2.52},{"code":"4676.T","name":"フジ・メディア・ホールディングス","bucket":"core","sector":"情報・通信業","surge":2.358,"z":1.74,"recent":242445800,"share_recent":0.035,"share_base":0.012,"share_delta":0.023,"last":4048.0,"pct":0.15},{"code":"4206.T","name":"アイカ工業","bucket":"core","sector":"化学","surge":2.327,"z":2.66,"recent":117538200,"share_recent":0.017,"share_base":0.005,"share_delta":0.012,"last":3693.0,"pct":-1.62},{"code":"9684.T","name":"スクウェア・エニックス・ホールディングス","bucket":"core","sector":"情報・通信業","surge":2.3,"z":2.0,"recent":258054850,"share_recent":0.038,"share_base":0.012,"share_delta":0.026,"last":2595.0,"pct":0.82},{"code":"4324.T","name":"電通グループ","bucket":"leader","sector":"サービス業","surge":2.292,"z":1.24,"recent":394181400,"share_recent":0.058,"share_base":0.022,"share_delta":0.036,"last":3340.0,"pct":4.77},{"code":"1820.T","name":"西松建設","bucket":"core","sector":"建設業","surge":2.284,"z":1.23,"recent":83872700,"share_recent":0.012,"share_base":0.004,"share_delta":0.008,"last":5404.0,"pct":1.45},{"code":"4182.T","name":"三菱瓦斯化学","bucket":"core","sector":"化学","surge":2.274,"z":1.34,"recent":641346700,"share_recent":0.094,"share_base":0.031,"share_delta":0.063,"last":4646.0,"pct":-0.87},{"code":"8377.T","name":"ほくほくフィナンシャルグループ","bucket":"core","sector":"銀行業","surge":2.268,"z":2.17,"recent":394565500,"share_recent":0.058,"share_base":0.019,"share_delta":0.038,"last":7545.0,"pct":6.31},{"code":"2267.T","name":"ヤクルト本社","bucket":"core","sector":"食料品","surge":2.258,"z":1.7,"recent":355223850,"share_recent":0.052,"share_base":0.018,"share_delta":0.034,"last":2829.5,"pct":0.23},{"code":"9301.T","name":"三菱倉庫","bucket":"core","sector":"倉庫・運輸関連業","surge":2.254,"z":2.25,"recent":193926250,"share_recent":0.028,"share_base":0.01,"share_delta":0.019,"last":1605.5,"pct":1.77},{"code":"5631.T","name":"日本製鋼所","bucket":"leader","sector":"機械","surge":2.249,"z":1.26,"recent":1238919600,"share_recent":0.181,"share_base":0.067,"share_delta":0.114,"last":7891.0,"pct":-0.94},{"code":"4716.T","name":"日本オラクル","bucket":"core","sector":"情報・通信業","surge":2.248,"z":2.23,"recent":305138300,"share_recent":0.045,"share_base":0.015,"share_delta":0.03,"last":8684.0,"pct":-2.49},{"code":"9962.T","name":"ミスミグループ本社","bucket":"core","sector":"卸売業","surge":2.243,"z":1.42,"recent":511234600,"share_recent":0.075,"share_base":0.026,"share_delta":0.049,"last":3950.0,"pct":-1.99},{"code":"4091.T","name":"日本酸素ホールディングス","bucket":"core","sector":"化学","surge":2.209,"z":1.06,"recent":268919200,"share_recent":0.039,"share_base":0.015,"share_delta":0.024,"last":6113.0,"pct":-2.22},{"code":"8331.T","name":"千葉銀行","bucket":"leader","sector":"銀行業","surge":2.205,"z":1.77,"recent":757249300,"share_recent":0.111,"share_base":0.039,"share_delta":0.072,"last":2712.5,"pct":5.18},{"code":"4202.T","name":"ダイセル","bucket":"core","sector":"化学","surge":2.183,"z":1.71,"recent":146759450,"share_recent":0.021,"share_base":0.008,"share_delta":0.014,"last":1394.0,"pct":-0.61},{"code":"7984.T","name":"コクヨ","bucket":"core","sector":"その他製品","surge":2.18,"z":1.86,"recent":90494570,"share_recent":0.013,"share_base":0.005,"share_delta":0.009,"last":848.5999755859375,"pct":3.11},{"code":"6473.T","name":"ジェイテクト","bucket":"leader","sector":"機械","surge":2.169,"z":2.08,"recent":290487950,"share_recent":0.042,"share_base":0.015,"share_delta":0.028,"last":2061.5,"pct":-0.07},{"code":"4544.T","name":"Ｈ．Ｕ．グループホールディングス","bucket":"core","sector":"サービス業","surge":2.164,"z":2.56,"recent":107244400,"share_recent":0.016,"share_base":0.005,"share_delta":0.011,"last":3332.0,"pct":-2.54},{"code":"4061.T","name":"デンカ","bucket":"leader","sector":"化学","surge":2.138,"z":3.08,"recent":358622500,"share_recent":0.052,"share_base":0.017,"share_delta":0.035,"last":3901.0,"pct":-6.61},{"code":"3289.T","name":"東急不動産ホールディングス","bucket":"leader","sector":"不動産業","surge":2.128,"z":2.84,"recent":375547000,"share_recent":0.055,"share_base":0.018,"share_delta":0.037,"last":1306.5,"pct":-2.9},{"code":"8591.T","name":"オリックス","bucket":"leader","sector":"その他金融業","surge":2.106,"z":1.76,"recent":1638212200,"share_recent":0.239,"share_base":0.087,"share_delta":0.152,"last":6410.0,"pct":1.46},{"code":"8086.T","name":"ニプロ","bucket":"core","sector":"精密機器","surge":2.09,"z":1.48,"recent":67755250,"share_recent":0.01,"share_base":0.004,"share_delta":0.006,"last":1557.0,"pct":-1.39},{"code":"5714.T","name":"ＤＯＷＡホールディングス","bucket":"leader","sector":"非鉄金属","surge":2.063,"z":2.99,"recent":521340500,"share_recent":0.076,"share_base":0.025,"share_delta":0.052,"last":8225.0,"pct":-7.85},{"code":"5076.T","name":"インフロニア・ホールディングス","bucket":"core","sector":"建設業","surge":2.063,"z":1.55,"recent":547300650,"share_recent":0.08,"share_base":0.03,"share_delta":0.05,"last":2914.0,"pct":8.59},{"code":"6849.T","name":"日本光電工業","bucket":"core","sector":"電気機器","surge":2.058,"z":1.68,"recent":100128100,"share_recent":0.015,"share_base":0.005,"share_delta":0.009,"last":1501.0,"pct":1.52},{"code":"6753.T","name":"シャープ","bucket":"leader","sector":"電気機器","surge":2.058,"z":1.05,"recent":214010289,"share_recent":0.031,"share_base":0.013,"share_delta":0.018,"last":647.2000122070312,"pct":-0.23},{"code":"4540.T","name":"ツムラ","bucket":"core","sector":"医薬品","surge":2.047,"z":0.78,"recent":94331300,"share_recent":0.014,"share_base":0.006,"share_delta":0.008,"last":3789.0,"pct":0.26},{"code":"7846.T","name":"パイロットコーポレーション","bucket":"core","sector":"その他製品","surge":2.043,"z":1.18,"recent":41432300,"share_recent":0.006,"share_base":0.002,"share_delta":0.004,"last":1775.5,"pct":1.86},{"code":"4203.T","name":"住友ベークライト","bucket":"core","sector":"化学","surge":2.042,"z":1.79,"recent":408241800,"share_recent":0.06,"share_base":0.021,"share_delta":0.038,"last":7106.0,"pct":-0.75},{"code":"6448.T","name":"ブラザー工業","bucket":"core","sector":"電気機器","surge":2.038,"z":1.31,"recent":233231000,"share_recent":0.034,"share_base":0.013,"share_delta":0.021,"last":3703.0,"pct":0.08},{"code":"8282.T","name":"ケーズホールディングス","bucket":"core","sector":"小売業","surge":2.034,"z":1.3,"recent":146267550,"share_recent":0.021,"share_base":0.009,"share_delta":0.013,"last":1828.5,"pct":-0.92},{"code":"4401.T","name":"ＡＤＥＫＡ","bucket":"core","sector":"化学","surge":2.032,"z":1.48,"recent":196890400,"share_recent":0.029,"share_base":0.01,"share_delta":0.018,"last":4145.0,"pct":-2.17},{"code":"1928.T","name":"積水ハウス","bucket":"leader","sector":"建設業","surge":2.025,"z":1.52,"recent":1011513700,"share_recent":0.148,"share_base":0.053,"share_delta":0.095,"last":3470.0,"pct":0.06},{"code":"1959.T","name":"クラフティア","bucket":"core","sector":"建設業","surge":2.02,"z":0.37,"recent":154071300,"share_recent":0.023,"share_base":0.01,"share_delta":0.013,"last":8888.0,"pct":-3.71},{"code":"7240.T","name":"ＮＯＫ","bucket":"core","sector":"輸送用機器","surge":2.017,"z":1.82,"recent":112032750,"share_recent":0.016,"share_base":0.006,"share_delta":0.01,"last":2894.0,"pct":-1.55},{"code":"7309.T","name":"シマノ","bucket":"core","sector":"輸送用機器","surge":2.005,"z":1.28,"recent":422573500,"share_recent":0.062,"share_base":0.023,"share_delta":0.038,"last":17090.0,"pct":-1.98},{"code":"5444.T","name":"大和工業","bucket":"core","sector":"鉄鋼","surge":2.0,"z":2.46,"recent":143166000,"share_recent":0.021,"share_base":0.007,"share_delta":0.014,"last":12330.0,"pct":-1.08},{"code":"9020.T","name":"東日本旅客鉄道","bucket":"leader","sector":"陸運業","surge":1.978,"z":1.32,"recent":639135100,"share_recent":0.093,"share_base":0.036,"share_delta":0.057,"last":3513.0,"pct":-0.59},{"code":"7313.T","name":"テイ・エス　テック","bucket":"core","sector":"輸送用機器","surge":1.975,"z":0.32,"recent":45302500,"share_recent":0.007,"share_base":0.003,"share_delta":0.004,"last":1742.5,"pct":-1.19},{"code":"4631.T","name":"ＤＩＣ","bucket":"core","sector":"化学","surge":1.965,"z":2.14,"recent":239403100,"share_recent":0.035,"share_base":0.012,"share_delta":0.023,"last":4653.0,"pct":-2.41},{"code":"4536.T","name":"参天製薬","bucket":"core","sector":"医薬品","surge":1.959,"z":2.04,"recent":306749100,"share_recent":0.045,"share_base":0.017,"share_delta":0.028,"last":2160.5,"pct":-2.81},{"code":"9627.T","name":"アインホールディングス","bucket":"core","sector":"小売業","surge":1.954,"z":1.24,"recent":58793700,"share_recent":0.009,"share_base":0.003,"share_delta":0.005,"last":5716.0,"pct":0.67},{"code":"9007.T","name":"小田急電鉄","bucket":"leader","sector":"陸運業","surge":1.954,"z":1.19,"recent":221086100,"share_recent":0.032,"share_base":0.013,"share_delta":0.019,"last":1697.5,"pct":0.47},{"code":"3038.T","name":"神戸物産","bucket":"core","sector":"卸売業","surge":1.941,"z":1.39,"recent":294098450,"share_recent":0.043,"share_base":0.017,"share_delta":0.026,"last":2690.5,"pct":-1.37},{"code":"9531.T","name":"東京瓦斯","bucket":"leader","sector":"電気・ガス業","surge":1.938,"z":1.71,"recent":557924800,"share_recent":0.081,"share_base":0.03,"share_delta":0.051,"last":6070.0,"pct":-0.48},{"code":"9602.T","name":"東宝","bucket":"leader","sector":"情報・通信業","surge":1.935,"z":1.35,"recent":321881000,"share_recent":0.047,"share_base":0.019,"share_delta":0.028,"last":1358.5,"pct":2.34},{"code":"1969.T","name":"高砂熱学工業","bucket":"core","sector":"建設業","surge":1.924,"z":1.73,"recent":275058900,"share_recent":0.04,"share_base":0.015,"share_delta":0.025,"last":4783.0,"pct":-6.84},{"code":"4680.T","name":"ラウンドワン","bucket":"core","sector":"サービス業","surge":1.916,"z":0.63,"recent":447726800,"share_recent":0.065,"share_base":0.029,"share_delta":0.036,"last":1242.0,"pct":1.22},{"code":"4768.T","name":"大塚商会","bucket":"core","sector":"情報・通信業","surge":1.914,"z":1.9,"recent":394304100,"share_recent":0.058,"share_base":0.022,"share_delta":0.035,"last":2926.0,"pct":2.04},{"code":"3635.T","name":"コーエーテクモホールディングス","bucket":"core","sector":"情報・通信業","surge":1.901,"z":1.18,"recent":141480750,"share_recent":0.021,"share_base":0.008,"share_delta":0.012,"last":1598.5,"pct":0.35},{"code":"3132.T","name":"マクニカホールディングス","bucket":"core","sector":"卸売業","surge":1.892,"z":0.89,"recent":208626500,"share_recent":0.03,"share_base":0.013,"share_delta":0.018,"last":3158.0,"pct":3.14},{"code":"6841.T","name":"横河電機","bucket":"leader","sector":"電気機器","surge":1.89,"z":1.6,"recent":483510500,"share_recent":0.071,"share_base":0.027,"share_delta":0.044,"last":5447.0,"pct":-2.05},{"code":"1332.T","name":"ニッスイ","bucket":"leader","sector":"水産・農林業","surge":1.883,"z":1.51,"recent":129126850,"share_recent":0.019,"share_base":0.007,"share_delta":0.011,"last":1283.0,"pct":-1.12},{"code":"5019.T","name":"出光興産","bucket":"leader","sector":"石油・石炭製品","surge":1.869,"z":1.7,"recent":397372550,"share_recent":0.058,"share_base":0.022,"share_delta":0.036,"last":1237.0,"pct":1.48},{"code":"7476.T","name":"アズワン","bucket":"core","sector":"卸売業","surge":1.868,"z":1.87,"recent":41812050,"share_recent":0.006,"share_base":0.002,"share_delta":0.004,"last":2415.5,"pct":2.63},{"code":"3116.T","name":"トヨタ紡織","bucket":"core","sector":"輸送用機器","surge":1.865,"z":0.56,"recent":141777050,"share_recent":0.021,"share_base":0.01,"share_delta":0.011,"last":2166.0,"pct":-2.74},{"code":"3048.T","name":"ビックカメラ","bucket":"core","sector":"小売業","surge":1.855,"z":1.21,"recent":68661600,"share_recent":0.01,"share_base":0.004,"share_delta":0.006,"last":1653.0,"pct":1.26},{"code":"7867.T","name":"タカラトミー","bucket":"core","sector":"その他製品","surge":1.854,"z":1.35,"recent":112470800,"share_recent":0.016,"share_base":0.007,"share_delta":0.01,"last":3287.0,"pct":1.29},{"code":"8129.T","name":"東邦ホールディングス","bucket":"core","sector":"卸売業","surge":1.849,"z":0.68,"recent":50124600,"share_recent":0.007,"share_base":0.003,"share_delta":0.004,"last":3968.0,"pct":1.43},{"code":"4733.T","name":"オービックビジネスコンサルタント","bucket":"core","sector":"情報・通信業","surge":1.846,"z":0.94,"recent":111090600,"share_recent":0.016,"share_base":0.007,"share_delta":0.009,"last":6483.0,"pct":-0.64},{"code":"9202.T","name":"ＡＮＡホールディングス","bucket":"leader","sector":"空運業","surge":1.843,"z":1.5,"recent":681603700,"share_recent":0.1,"share_base":0.041,"share_delta":0.059,"last":3040.0,"pct":-3.31},{"code":"9147.T","name":"ＮＩＰＰＯＮＥＸＰＲＥＳＳホールディングス","bucket":"leader","sector":"陸運業","surge":1.83,"z":0.93,"recent":540179200,"share_recent":0.079,"share_base":0.035,"share_delta":0.044,"last":5435.0,"pct":3.58},{"code":"4613.T","name":"関西ペイント","bucket":"core","sector":"化学","surge":1.827,"z":1.01,"recent":267045300,"share_recent":0.039,"share_base":0.016,"share_delta":0.023,"last":2694.0,"pct":-0.94},{"code":"4503.T","name":"アステラス製薬","bucket":"leader","sector":"医薬品","surge":1.827,"z":1.43,"recent":953630550,"share_recent":0.139,"share_base":0.056,"share_delta":0.084,"last":2145.0,"pct":-1.33},{"code":"7186.T","name":"横浜フィナンシャルグループ","bucket":"leader","sector":"銀行業","surge":1.82,"z":0.92,"recent":727529250,"share_recent":0.106,"share_base":0.046,"share_delta":0.061,"last":1871.5,"pct":4.2},{"code":"7550.T","name":"ゼンショーホールディングス","bucket":"core","sector":"小売業","surge":1.809,"z":0.91,"recent":560044600,"share_recent":0.082,"share_base":0.035,"share_delta":0.047,"last":8922.0,"pct":7.53},{"code":"6417.T","name":"ＳＡＮＫＹＯ","bucket":"core","sector":"機械","surge":1.806,"z":1.06,"recent":107180800,"share_recent":0.016,"share_base":0.007,"share_delta":0.009,"last":1666.5,"pct":1.8},{"code":"2784.T","name":"アルフレッサ　ホールディングス","bucket":"core","sector":"卸売業","surge":1.805,"z":0.98,"recent":77891450,"share_recent":0.011,"share_base":0.005,"share_delta":0.006,"last":2229.0,"pct":1.66},{"code":"4452.T","name":"花王","bucket":"leader","sector":"化学","surge":1.799,"z":0.79,"recent":729387300,"share_recent":0.107,"share_base":0.047,"share_delta":0.059,"last":3267.0,"pct":-2.01},{"code":"8439.T","name":"東京センチュリー","bucket":"core","sector":"その他金融業","surge":1.798,"z":1.55,"recent":123363500,"share_recent":0.018,"share_base":0.007,"share_delta":0.011,"last":2564.0,"pct":2.72},{"code":"4194.T","name":"ビジョナル","bucket":"core","sector":"情報・通信業","surge":1.798,"z":1.09,"recent":182351700,"share_recent":0.027,"share_base":0.011,"share_delta":0.016,"last":8201.0,"pct":2.32},{"code":"4901.T","name":"富士フイルムホールディングス","bucket":"leader","sector":"化学","surge":1.793,"z":0.5,"recent":1042195100,"share_recent":0.152,"share_base":0.076,"share_delta":0.077,"last":3581.0,"pct":0.79},{"code":"3231.T","name":"野村不動産ホールディングス","bucket":"core","sector":"不動産業","surge":1.791,"z":1.51,"recent":305368291,"share_recent":0.045,"share_base":0.018,"share_delta":0.027,"last":934.7000122070312,"pct":-2.14},{"code":"8020.T","name":"兼松","bucket":"core","sector":"卸売業","surge":1.789,"z":0.54,"recent":82398050,"share_recent":0.012,"share_base":0.006,"share_delta":0.006,"last":2047.5,"pct":-2.03},{"code":"8174.T","name":"日本瓦斯","bucket":"core","sector":"小売業","surge":1.787,"z":1.32,"recent":87707100,"share_recent":0.013,"share_base":0.005,"share_delta":0.007,"last":2893.0,"pct":1.3},{"code":"8830.T","name":"住友不動産","bucket":"leader","sector":"不動産業","surge":1.786,"z":0.79,"recent":843385000,"share_recent":0.123,"share_base":0.055,"share_delta":0.068,"last":3785.0,"pct":-2.92},{"code":"2607.T","name":"不二製油","bucket":"core","sector":"食料品","surge":1.782,"z":1.9,"recent":106030700,"share_recent":0.015,"share_base":0.006,"share_delta":0.01,"last":4096.0,"pct":1.97},{"code":"6302.T","name":"住友重機械工業","bucket":"leader","sector":"機械","surge":1.779,"z":1.23,"recent":310713300,"share_recent":0.045,"share_base":0.019,"share_delta":0.027,"last":5131.0,"pct":-2.04},{"code":"6326.T","name":"クボタ","bucket":"leader","sector":"機械","surge":1.777,"z":1.14,"recent":605749550,"share_recent":0.088,"share_base":0.038,"share_delta":0.051,"last":2729.0,"pct":1.39},{"code":"2503.T","name":"キリンホールディングス","bucket":"leader","sector":"食料品","surge":1.772,"z":1.24,"recent":721576150,"share_recent":0.105,"share_base":0.044,"share_delta":0.062,"last":2906.0,"pct":2.98},{"code":"9022.T","name":"東海旅客鉄道","bucket":"leader","sector":"陸運業","surge":1.767,"z":0.48,"recent":898822500,"share_recent":0.131,"share_base":0.065,"share_delta":0.067,"last":3653.0,"pct":3.13},{"code":"2269.T","name":"明治ホールディングス","bucket":"leader","sector":"食料品","surge":1.767,"z":1.27,"recent":226843800,"share_recent":0.033,"share_base":0.014,"share_delta":0.019,"last":3831.0,"pct":-1.03},{"code":"4527.T","name":"ロート製薬","bucket":"core","sector":"医薬品","surge":1.766,"z":0.27,"recent":176973900,"share_recent":0.026,"share_base":0.014,"share_delta":0.012,"last":2464.0,"pct":2.33},{"code":"2206.T","name":"江崎グリコ","bucket":"core","sector":"食料品","surge":1.763,"z":1.29,"recent":120346600,"share_recent":0.018,"share_base":0.007,"share_delta":0.01,"last":5254.0,"pct":-1.83},{"code":"4911.T","name":"資生堂","bucket":"leader","sector":"化学","surge":1.756,"z":1.73,"recent":781381700,"share_recent":0.114,"share_base":0.047,"share_delta":0.068,"last":2757.0,"pct":-0.9},{"code":"3107.T","name":"ダイワボウホールディングス","bucket":"core","sector":"卸売業","surge":1.753,"z":2.04,"recent":108505100,"share_recent":0.016,"share_base":0.006,"share_delta":0.01,"last":3396.0,"pct":-2.92},{"code":"6506.T","name":"安川電機","bucket":"leader","sector":"電気機器","surge":1.753,"z":0.67,"recent":4345477600,"share_recent":0.635,"share_base":0.294,"share_delta":0.341,"last":6850.0,"pct":0.04},{"code":"9759.T","name":"ＮＳＤ","bucket":"core","sector":"情報・通信業","surge":1.747,"z":1.5,"recent":59404650,"share_recent":0.009,"share_base":0.004,"share_delta":0.005,"last":2663.0,"pct":2.01},{"code":"7911.T","name":"ＴＯＰＰＡＮホールディングス","bucket":"leader","sector":"その他製品","surge":1.742,"z":0.77,"recent":587000800,"share_recent":0.086,"share_base":0.039,"share_delta":0.047,"last":5233.0,"pct":0.15},{"code":"9468.T","name":"ＫＡＤＯＫＡＷＡ","bucket":"core","sector":"情報・通信業","surge":1.733,"z":1.44,"recent":184580300,"share_recent":0.027,"share_base":0.011,"share_delta":0.016,"last":3781.0,"pct":2.44},{"code":"4523.T","name":"エーザイ","bucket":"leader","sector":"医薬品","surge":1.732,"z":1.2,"recent":609289700,"share_recent":0.089,"share_base":0.038,"share_delta":0.051,"last":4267.0,"pct":-0.56},{"code":"6532.T","name":"ベイカレント","bucket":"leader","sector":"サービス業","surge":1.731,"z":0.99,"recent":1000970900,"share_recent":0.146,"share_base":0.065,"share_delta":0.081,"last":6689.0,"pct":-0.82},{"code":"9401.T","name":"ＴＢＳホールディングス","bucket":"core","sector":"情報・通信業","surge":1.73,"z":1.54,"recent":186529600,"share_recent":0.027,"share_base":0.011,"share_delta":0.017,"last":6474.0,"pct":0.83},{"code":"5844.T","name":"京都フィナンシャルグループ","bucket":"core","sector":"銀行業","surge":1.729,"z":0.37,"recent":411159800,"share_recent":0.06,"share_base":0.03,"share_delta":0.03,"last":4766.0,"pct":2.41},{"code":"3407.T","name":"旭化成","bucket":"leader","sector":"化学","surge":1.72,"z":1.19,"recent":740416300,"share_recent":0.108,"share_base":0.048,"share_delta":0.06,"last":1843.5,"pct":2.67},{"code":"4684.T","name":"オービック","bucket":"core","sector":"情報・通信業","surge":1.72,"z":1.31,"recent":565127500,"share_recent":0.083,"share_base":0.035,"share_delta":0.048,"last":4117.0,"pct":2.03},{"code":"8227.T","name":"しまむら","bucket":"core","sector":"小売業","surge":1.719,"z":1.16,"recent":227864800,"share_recent":0.033,"share_base":0.014,"share_delta":0.019,"last":3430.0,"pct":0.44},{"code":"1333.T","name":"Ｕｍｉｏｓ","bucket":"core","sector":"水産・農林業","surge":1.716,"z":1.34,"recent":62663350,"share_recent":0.009,"share_base":0.004,"share_delta":0.005,"last":1319.5,"pct":-0.04},{"code":"8630.T","name":"ＳＯＭＰＯホールディングス","bucket":"leader","sector":"保険業","surge":1.711,"z":1.29,"recent":1346550900,"share_recent":0.197,"share_base":0.084,"share_delta":0.113,"last":6612.0,"pct":-0.8},{"code":"9744.T","name":"メイテックグループホールディングス","bucket":"core","sector":"サービス業","surge":1.696,"z":0.95,"recent":81450500,"share_recent":0.012,"share_base":0.005,"share_delta":0.007,"last":3191.0,"pct":0.69},{"code":"6269.T","name":"三井海洋開発","bucket":"core","sector":"機械","surge":1.696,"z":0.27,"recent":606073400,"share_recent":0.089,"share_base":0.048,"share_delta":0.041,"last":9868.0,"pct":8.26},{"code":"3626.T","name":"ＴＩＳ","bucket":"core","sector":"情報・通信業","surge":1.695,"z":0.54,"recent":266325300,"share_recent":0.039,"share_base":0.019,"share_delta":0.02,"last":3452.0,"pct":2.07},{"code":"4021.T","name":"日産化学","bucket":"leader","sector":"化学","surge":1.694,"z":1.55,"recent":627465300,"share_recent":0.092,"share_base":0.038,"share_delta":0.053,"last":8112.0,"pct":-4.01},{"code":"9449.T","name":"ＧＭＯインターネットグループ","bucket":"core","sector":"情報・通信業","surge":1.693,"z":0.28,"recent":148048000,"share_recent":0.022,"share_base":0.012,"share_delta":0.01,"last":3797.0,"pct":4.74},{"code":"6457.T","name":"グローリー","bucket":"core","sector":"機械","surge":1.691,"z":1.24,"recent":73964900,"share_recent":0.011,"share_base":0.004,"share_delta":0.006,"last":4146.0,"pct":2.37},{"code":"4704.T","name":"トレンドマイクロ","bucket":"leader","sector":"情報・通信業","surge":1.69,"z":0.75,"recent":389047900,"share_recent":0.057,"share_base":0.027,"share_delta":0.03,"last":6230.0,"pct":-3.56},{"code":"4043.T","name":"トクヤマ","bucket":"leader","sector":"化学","surge":1.689,"z":1.01,"recent":323835900,"share_recent":0.047,"share_base":0.021,"share_delta":0.026,"last":4569.0,"pct":-6.74},{"code":"4681.T","name":"リゾートトラスト","bucket":"core","sector":"サービス業","surge":1.688,"z":1.52,"recent":66417450,"share_recent":0.01,"share_base":0.004,"share_delta":0.006,"last":1742.0,"pct":-2.71},{"code":"5334.T","name":"日本特殊陶業","bucket":"core","sector":"ガラス・土石製品","surge":1.681,"z":1.22,"recent":763852000,"share_recent":0.112,"share_base":0.048,"share_delta":0.064,"last":10415.0,"pct":-2.66},{"code":"6479.T","name":"ミネベアミツミ","bucket":"leader","sector":"電気機器","surge":1.68,"z":0.45,"recent":1801112900,"share_recent":0.263,"share_base":0.129,"share_delta":0.134,"last":4329.0,"pct":-8.59},{"code":"2413.T","name":"エムスリー","bucket":"leader","sector":"サービス業","surge":1.675,"z":1.07,"recent":558676750,"share_recent":0.082,"share_base":0.035,"share_delta":0.047,"last":1874.5,"pct":-0.08},{"code":"3591.T","name":"ワコールホールディングス","bucket":"core","sector":"繊維製品","surge":1.675,"z":1.58,"recent":32186400,"share_recent":0.005,"share_base":0.002,"share_delta":0.003,"last":4468.0,"pct":1.2},{"code":"8729.T","name":"ソニーフィナンシャルグループ","bucket":"core","sector":"保険業","surge":1.664,"z":0.44,"recent":667508880,"share_recent":0.097,"share_base":0.051,"share_delta":0.047,"last":147.0,"pct":0.2},{"code":"4666.T","name":"パーク２４","bucket":"core","sector":"不動産業","surge":1.664,"z":1.16,"recent":144103600,"share_recent":0.021,"share_base":0.009,"share_delta":0.012,"last":2014.0,"pct":-0.54},{"code":"9697.T","name":"カプコン","bucket":"core","sector":"情報・通信業","surge":1.661,"z":0.79,"recent":539893800,"share_recent":0.079,"share_base":0.038,"share_delta":0.04,"last":3336.0,"pct":1.77},{"code":"7733.T","name":"オリンパス","bucket":"leader","sector":"精密機器","surge":1.657,"z":0.51,"recent":484292400,"share_recent":0.071,"share_base":0.035,"share_delta":0.035,"last":1737.0,"pct":-1.33},{"code":"5021.T","name":"コスモエネルギーホールディングス","bucket":"core","sector":"石油・石炭製品","surge":1.656,"z":1.01,"recent":166733800,"share_recent":0.024,"share_base":0.011,"share_delta":0.014,"last":3850.0,"pct":-1.58},{"code":"6856.T","name":"堀場製作所","bucket":"core","sector":"電気機器","surge":1.651,"z":0.57,"recent":496817500,"share_recent":0.073,"share_base":0.035,"share_delta":0.037,"last":26420.0,"pct":-0.19},{"code":"4967.T","name":"小林製薬","bucket":"core","sector":"化学","surge":1.648,"z":0.72,"recent":84046400,"share_recent":0.012,"share_base":0.006,"share_delta":0.007,"last":5675.0,"pct":1.76},{"code":"9072.T","name":"ニッコンホールディングス","bucket":"core","sector":"陸運業","surge":1.647,"z":0.84,"recent":131650900,"share_recent":0.019,"share_base":0.008,"share_delta":0.011,"last":5446.0,"pct":-2.14},{"code":"5929.T","name":"三和ホールディングス","bucket":"core","sector":"金属製品","surge":1.642,"z":0.85,"recent":137043200,"share_recent":0.02,"share_base":0.009,"share_delta":0.011,"last":3729.0,"pct":-2.69},{"code":"9041.T","name":"近鉄グループホールディングス","bucket":"core","sector":"陸運業","surge":1.642,"z":1.41,"recent":139218200,"share_recent":0.02,"share_base":0.009,"share_delta":0.012,"last":3456.0,"pct":0.88},{"code":"8595.T","name":"ジャフコ　グループ","bucket":"core","sector":"証券、商品先物取引業","surge":1.638,"z":0.78,"recent":73544800,"share_recent":0.011,"share_base":0.005,"share_delta":0.006,"last":2355.5,"pct":-1.67},{"code":"4272.T","name":"日本化薬","bucket":"core","sector":"化学","surge":1.634,"z":1.36,"recent":107137200,"share_recent":0.016,"share_base":0.007,"share_delta":0.009,"last":1978.5,"pct":-1.96},{"code":"6951.T","name":"日本電子","bucket":"core","sector":"電気機器","surge":1.631,"z":0.15,"recent":235816400,"share_recent":0.034,"share_base":0.02,"share_delta":0.014,"last":7270.0,"pct":-1.64},{"code":"5232.T","name":"住友大阪セメント","bucket":"core","sector":"ガラス・土石製品","surge":1.629,"z":0.82,"recent":143113300,"share_recent":0.021,"share_base":0.01,"share_delta":0.011,"last":5387.0,"pct":-7.36},{"code":"3360.T","name":"シップヘルスケアホールディングス","bucket":"core","sector":"卸売業","surge":1.629,"z":1.05,"recent":40807900,"share_recent":0.006,"share_base":0.003,"share_delta":0.003,"last":2272.5,"pct":-0.44},{"code":"4307.T","name":"野村総合研究所","bucket":"leader","sector":"情報・通信業","surge":1.628,"z":0.86,"recent":970651900,"share_recent":0.142,"share_base":0.067,"share_delta":0.074,"last":5002.0,"pct":0.77},{"code":"7259.T","name":"アイシン","bucket":"core","sector":"輸送用機器","surge":1.622,"z":0.78,"recent":380680050,"share_recent":0.056,"share_base":0.027,"share_delta":0.029,"last":2287.0,"pct":0.84},{"code":"6465.T","name":"ホシザキ","bucket":"core","sector":"機械","surge":1.622,"z":0.44,"recent":201684100,"share_recent":0.029,"share_base":0.015,"share_delta":0.015,"last":5552.0,"pct":-2.46},{"code":"3291.T","name":"飯田グループホールディングス","bucket":"core","sector":"不動産業","surge":1.618,"z":0.6,"recent":81674250,"share_recent":0.012,"share_base":0.006,"share_delta":0.006,"last":2210.0,"pct":0.09},{"code":"7453.T","name":"良品計画","bucket":"leader","sector":"小売業","surge":1.618,"z":0.44,"recent":1658001100,"share_recent":0.242,"share_base":0.13,"share_delta":0.112,"last":3745.0,"pct":2.32},{"code":"7616.T","name":"コロワイド","bucket":"core","sector":"小売業","surge":1.617,"z":0.33,"recent":47587600,"share_recent":0.007,"share_base":0.004,"share_delta":0.003,"last":1909.0,"pct":3.16},{"code":"5101.T","name":"横浜ゴム","bucket":"leader","sector":"ゴム製品","surge":1.617,"z":0.89,"recent":655155700,"share_recent":0.096,"share_base":0.044,"share_delta":0.052,"last":7479.0,"pct":-3.11},{"code":"4528.T","name":"小野薬品工業","bucket":"core","sector":"医薬品","surge":1.614,"z":1.13,"recent":211871350,"share_recent":0.031,"share_base":0.014,"share_delta":0.017,"last":2442.0,"pct":-0.55},{"code":"6370.T","name":"栗田工業","bucket":"core","sector":"機械","surge":1.613,"z":0.73,"recent":350948700,"share_recent":0.051,"share_base":0.024,"share_delta":0.027,"last":9010.0,"pct":0.0},{"code":"2327.T","name":"日鉄ソリューションズ","bucket":"core","sector":"情報・通信業","surge":1.612,"z":0.66,"recent":87867600,"share_recent":0.013,"share_base":0.006,"share_delta":0.007,"last":3731.0,"pct":3.18},{"code":"7459.T","name":"メディパルホールディングス","bucket":"core","sector":"卸売業","surge":1.611,"z":0.13,"recent":65135800,"share_recent":0.01,"share_base":0.006,"share_delta":0.004,"last":2701.5,"pct":-0.06},{"code":"3923.T","name":"ラクス","bucket":"core","sector":"情報・通信業","surge":1.61,"z":0.51,"recent":158351350,"share_recent":0.023,"share_base":0.011,"share_delta":0.012,"last":1031.5,"pct":0.88},{"code":"4507.T","name":"塩野義製薬","bucket":"leader","sector":"医薬品","surge":1.61,"z":0.53,"recent":472615050,"share_recent":0.069,"share_base":0.036,"share_delta":0.033,"last":2813.5,"pct":-3.43},{"code":"1802.T","name":"大林組","bucket":"leader","sector":"建設業","surge":1.607,"z":0.92,"recent":553697800,"share_recent":0.081,"share_base":0.037,"share_delta":0.043,"last":3234.0,"pct":-3.17},{"code":"1605.T","name":"ＩＮＰＥＸ","bucket":"leader","sector":"鉱業","surge":1.607,"z":0.69,"recent":1189928900,"share_recent":0.174,"share_base":0.084,"share_delta":0.089,"last":3408.0,"pct":5.51},{"code":"9143.T","name":"ＳＧホールディングス","bucket":"core","sector":"陸運業","surge":1.603,"z":0.75,"recent":117187500,"share_recent":0.017,"share_base":0.008,"share_delta":0.009,"last":1599.5,"pct":2.11},{"code":"2593.T","name":"伊藤園","bucket":"core","sector":"食料品","surge":1.603,"z":0.14,"recent":71618100,"share_recent":0.01,"share_base":0.006,"share_delta":0.004,"last":2994.5,"pct":1.59},{"code":"9003.T","name":"相鉄ホールディングス","bucket":"core","sector":"陸運業","surge":1.599,"z":1.34,"recent":46399450,"share_recent":0.007,"share_base":0.003,"share_delta":0.004,"last":2548.0,"pct":2.19},{"code":"6178.T","name":"日本郵政","bucket":"leader","sector":"サービス業","surge":1.597,"z":1.27,"recent":1103727800,"share_recent":0.161,"share_base":0.068,"share_delta":0.093,"last":2352.5,"pct":3.68},{"code":"2229.T","name":"カルビー","bucket":"core","sector":"食料品","surge":1.588,"z":0.39,"recent":72269600,"share_recent":0.011,"share_base":0.005,"share_delta":0.005,"last":3007.0,"pct":-0.1},{"code":"8354.T","name":"ふくおかフィナンシャルグループ","bucket":"leader","sector":"銀行業","surge":1.588,"z":0.69,"recent":410770500,"share_recent":0.06,"share_base":0.029,"share_delta":0.031,"last":7338.0,"pct":5.01},{"code":"3092.T","name":"ＺＯＺＯ","bucket":"leader","sector":"小売業","surge":1.587,"z":0.6,"recent":293701650,"share_recent":0.043,"share_base":0.021,"share_delta":0.022,"last":1177.5,"pct":0.51},{"code":"8060.T","name":"キヤノンマーケティングジャパン","bucket":"core","sector":"卸売業","surge":1.579,"z":1.07,"recent":97049100,"share_recent":0.014,"share_base":0.006,"share_delta":0.008,"last":3543.0,"pct":1.78},{"code":"9042.T","name":"阪急阪神ホールディングス","bucket":"core","sector":"陸運業","surge":1.578,"z":1.05,"recent":542269300,"share_recent":0.079,"share_base":0.036,"share_delta":0.043,"last":4703.0,"pct":5.31},{"code":"8697.T","name":"日本取引所グループ","bucket":"leader","sector":"その他金融業","surge":1.576,"z":0.78,"recent":538415300,"share_recent":0.079,"share_base":0.038,"share_delta":0.041,"last":2111.0,"pct":-1.49},{"code":"7167.T","name":"めぶきフィナンシャルグループ","bucket":"core","sector":"銀行業","surge":1.569,"z":1.16,"recent":390622000,"share_recent":0.057,"share_base":0.026,"share_delta":0.031,"last":1550.0,"pct":4.1},{"code":"9031.T","name":"西日本鉄道","bucket":"core","sector":"陸運業","surge":1.568,"z":0.13,"recent":34178150,"share_recent":0.005,"share_base":0.003,"share_delta":0.002,"last":2998.0,"pct":2.22},{"code":"4042.T","name":"東ソー","bucket":"leader","sector":"化学","surge":1.562,"z":1.08,"recent":305649050,"share_recent":0.045,"share_base":0.02,"share_delta":0.024,"last":2695.0,"pct":-5.11},{"code":"7276.T","name":"小糸製作所","bucket":"core","sector":"電気機器","surge":1.559,"z":0.73,"recent":105136250,"share_recent":0.015,"share_base":0.008,"share_delta":0.008,"last":2530.0,"pct":-2.37},{"code":"6436.T","name":"アマノ","bucket":"core","sector":"機械","surge":1.559,"z":0.77,"recent":82143400,"share_recent":0.012,"share_base":0.006,"share_delta":0.006,"last":3730.0,"pct":0.32},{"code":"9069.T","name":"センコーグループホールディングス","bucket":"core","sector":"陸運業","surge":1.559,"z":0.53,"recent":61224900,"share_recent":0.009,"share_base":0.004,"share_delta":0.005,"last":2049.0,"pct":4.46},{"code":"7269.T","name":"スズキ","bucket":"leader","sector":"輸送用機器","surge":1.558,"z":0.52,"recent":1389825950,"share_recent":0.203,"share_base":0.105,"share_delta":0.098,"last":2017.5,"pct":-3.88},{"code":"6645.T","name":"オムロン","bucket":"leader","sector":"電気機器","surge":1.556,"z":0.54,"recent":721124900,"share_recent":0.105,"share_base":0.053,"share_delta":0.052,"last":5866.0,"pct":0.0},{"code":"4927.T","name":"ポーラ・オルビスホールディングス","bucket":"core","sector":"化学","surge":1.549,"z":0.15,"recent":57675650,"share_recent":0.008,"share_base":0.005,"share_delta":0.004,"last":1324.5,"pct":0.57},{"code":"3994.T","name":"マネーフォワード","bucket":"core","sector":"情報・通信業","surge":1.547,"z":0.27,"recent":181866800,"share_recent":0.027,"share_base":0.014,"share_delta":0.012,"last":4982.0,"pct":9.59},{"code":"8725.T","name":"ＭＳ＆ＡＤインシュアランスグループホールディングス","bucket":"leader","sector":"保険業","surge":1.544,"z":0.22,"recent":1510031400,"share_recent":0.221,"share_base":0.128,"share_delta":0.092,"last":4483.0,"pct":0.95},{"code":"9983.T","name":"ファーストリテイリング","bucket":"leader","sector":"小売(SPA)","surge":1.529,"z":0.45,"recent":8264232000,"share_recent":1.207,"share_base":0.901,"share_delta":0.306,"last":81560.0,"pct":-2.08},{"code":"8015.T","name":"豊田通商","bucket":"leader","sector":"卸売業","surge":1.527,"z":0.52,"recent":802299400,"share_recent":0.117,"share_base":0.061,"share_delta":0.056,"last":6097.0,"pct":-1.68},{"code":"5020.T","name":"ＥＮＥＯＳホールディングス","bucket":"leader","sector":"石油・石炭製品","surge":1.525,"z":0.46,"recent":476193650,"share_recent":0.07,"share_base":0.037,"share_delta":0.033,"last":1252.5,"pct":1.42},{"code":"9048.T","name":"名古屋鉄道","bucket":"core","sector":"陸運業","surge":1.524,"z":0.76,"recent":106282350,"share_recent":0.016,"share_base":0.008,"share_delta":0.008,"last":1867.0,"pct":0.32},{"code":"3064.T","name":"ＭｏｎｏｔａＲＯ","bucket":"core","sector":"小売業","surge":1.52,"z":0.27,"recent":317621450,"share_recent":0.046,"share_base":0.026,"share_delta":0.021,"last":1964.0,"pct":2.48},{"code":"7211.T","name":"三菱自動車工業","bucket":"leader","sector":"輸送用機器","surge":1.518,"z":0.64,"recent":246639662,"share_recent":0.036,"share_base":0.018,"share_delta":0.018,"last":329.5,"pct":-0.45},{"code":"2871.T","name":"ニチレイ","bucket":"leader","sector":"食料品","surge":1.516,"z":0.49,"recent":179149500,"share_recent":0.026,"share_base":0.014,"share_delta":0.012,"last":2164.5,"pct":-1.32},{"code":"2432.T","name":"ディー・エヌ・エー","bucket":"leader","sector":"情報・通信業","surge":1.514,"z":0.49,"recent":429801900,"share_recent":0.063,"share_base":0.033,"share_delta":0.03,"last":2538.0,"pct":-5.72},{"code":"4186.T","name":"東京応化工業","bucket":"core","sector":"化学","surge":1.513,"z":0.84,"recent":786418000,"share_recent":0.115,"share_base":0.055,"share_delta":0.059,"last":10140.0,"pct":-0.93},{"code":"3197.T","name":"すかいらーくホールディングス","bucket":"core","sector":"小売業","surge":1.505,"z":0.29,"recent":337133350,"share_recent":0.049,"share_base":0.028,"share_delta":0.021,"last":2952.5,"pct":3.34},{"code":"2810.T","name":"ハウス食品グループ本社","bucket":"core","sector":"食料品","surge":1.503,"z":0.42,"recent":93644800,"share_recent":0.014,"share_base":0.007,"share_delta":0.007,"last":3872.0,"pct":1.02},{"code":"4626.T","name":"太陽ホールディングス","bucket":"core","sector":"化学","surge":1.502,"z":0.18,"recent":151163600,"share_recent":0.022,"share_base":0.013,"share_delta":0.009,"last":4876.0,"pct":-2.17},{"code":"3397.T","name":"トリドールホールディングス","bucket":"core","sector":"小売業","surge":1.501,"z":0.55,"recent":102435200,"share_recent":0.015,"share_base":0.008,"share_delta":0.007,"last":4018.0,"pct":2.11},{"code":"2371.T","name":"カカクコム","bucket":"core","sector":"サービス業","surge":1.497,"z":0.05,"recent":169630100,"share_recent":0.025,"share_base":0.016,"share_delta":0.009,"last":3635.0,"pct":1.42},{"code":"7532.T","name":"パン・パシフィック・インターナショナルホールディングス","bucket":"leader","sector":"小売業","surge":1.492,"z":0.9,"recent":664951109,"share_recent":0.097,"share_base":0.048,"share_delta":0.05,"last":867.2999877929688,"pct":2.96},{"code":"9044.T","name":"ＮＡＮＫＡＩ","bucket":"core","sector":"陸運業","surge":1.492,"z":0.8,"recent":72561450,"share_recent":0.011,"share_base":0.005,"share_delta":0.005,"last":2978.5,"pct":4.47},{"code":"3088.T","name":"マツキヨココカラ＆カンパニー","bucket":"core","sector":"小売業","surge":1.491,"z":0.36,"recent":297148250,"share_recent":0.043,"share_base":0.023,"share_delta":0.02,"last":2480.0,"pct":1.72},{"code":"7752.T","name":"リコー","bucket":"leader","sector":"電気機器","surge":1.489,"z":0.64,"recent":206951550,"share_recent":0.03,"share_base":0.015,"share_delta":0.015,"last":1472.5,"pct":2.61},{"code":"1801.T","name":"大成建設","bucket":"leader","sector":"建設業","surge":1.487,"z":0.42,"recent":806564000,"share_recent":0.118,"share_base":0.064,"share_delta":0.054,"last":13995.0,"pct":-4.8},{"code":"6544.T","name":"ジャパンエレベーターサービスホールディングス","bucket":"core","sector":"サービス業","surge":1.486,"z":0.67,"recent":67695000,"share_recent":0.01,"share_base":0.005,"share_delta":0.005,"last":1852.0,"pct":1.17},{"code":"8750.T","name":"第一ライフグループ","bucket":"leader","sector":"保険業","surge":1.485,"z":0.65,"recent":1002881000,"share_recent":0.146,"share_base":0.076,"share_delta":0.071,"last":1865.5,"pct":1.17},{"code":"6472.T","name":"ＮＴＮ","bucket":"leader","sector":"機械","surge":1.476,"z":0.87,"recent":123577709,"share_recent":0.018,"share_base":0.009,"share_delta":0.009,"last":387.5,"pct":-3.61},{"code":"7731.T","name":"ニコン","bucket":"leader","sector":"精密機器","surge":1.475,"z":0.91,"recent":217475450,"share_recent":0.032,"share_base":0.015,"share_delta":0.016,"last":2142.0,"pct":-3.16},{"code":"9831.T","name":"ヤマダホールディングス","bucket":"core","sector":"小売業","surge":1.474,"z":0.87,"recent":196217557,"share_recent":0.029,"share_base":0.014,"share_delta":0.015,"last":661.7999877929688,"pct":3.68},{"code":"1808.T","name":"長谷工コーポレーション","bucket":"leader","sector":"建設業","surge":1.47,"z":0.9,"recent":164317300,"share_recent":0.024,"share_base":0.011,"share_delta":0.013,"last":2761.5,"pct":-3.58},{"code":"2212.T","name":"山崎製パン","bucket":"core","sector":"食料品","surge":1.467,"z":0.49,"recent":77748300,"share_recent":0.011,"share_base":0.006,"share_delta":0.005,"last":3265.0,"pct":-0.55},{"code":"3659.T","name":"ネクソン","bucket":"leader","sector":"情報・通信業","surge":1.465,"z":0.58,"recent":313577950,"share_recent":0.046,"share_base":0.024,"share_delta":0.022,"last":2263.5,"pct":-1.46},{"code":"9076.T","name":"セイノーホールディングス","bucket":"core","sector":"陸運業","surge":1.464,"z":0.75,"recent":60986500,"share_recent":0.009,"share_base":0.004,"share_delta":0.005,"last":2698.5,"pct":0.94},{"code":"6952.T","name":"カシオ計算機","bucket":"core","sector":"電気機器","surge":1.462,"z":0.44,"recent":157344200,"share_recent":0.023,"share_base":0.012,"share_delta":0.011,"last":1848.0,"pct":0.22},{"code":"8056.T","name":"ＢＩＰＲＯＧＹ","bucket":"core","sector":"情報・通信業","surge":1.462,"z":0.33,"recent":133434400,"share_recent":0.019,"share_base":0.011,"share_delta":0.009,"last":4609.0,"pct":0.63},{"code":"1963.T","name":"日揮ホールディングス","bucket":"leader","sector":"建設業","surge":1.462,"z":0.52,"recent":330826550,"share_recent":0.048,"share_base":0.026,"share_delta":0.023,"last":2331.5,"pct":-6.81},{"code":"4114.T","name":"日本触媒","bucket":"core","sector":"化学","surge":1.46,"z":1.03,"recent":85645050,"share_recent":0.013,"share_base":0.006,"share_delta":0.007,"last":2084.5,"pct":-0.36},{"code":"8424.T","name":"芙蓉総合リース","bucket":"core","sector":"その他金融業","surge":1.457,"z":-0.09,"recent":61500900,"share_recent":0.009,"share_base":0.006,"share_delta":0.003,"last":4266.0,"pct":0.71},{"code":"9766.T","name":"コナミグループ","bucket":"leader","sector":"情報・通信業","surge":1.456,"z":0.77,"recent":639893000,"share_recent":0.093,"share_base":0.046,"share_delta":0.047,"last":18430.0,"pct":-3.25},{"code":"9506.T","name":"東北電力","bucket":"core","sector":"電気・ガス業","surge":1.455,"z":0.67,"recent":216570350,"share_recent":0.032,"share_base":0.016,"share_delta":0.016,"last":1095.5,"pct":2.34},{"code":"3288.T","name":"オープンハウスグループ","bucket":"core","sector":"不動産業","surge":1.45,"z":0.44,"recent":236020100,"share_recent":0.034,"share_base":0.018,"share_delta":0.016,"last":8648.0,"pct":2.03},{"code":"3778.T","name":"さくらインターネット","bucket":"hot","sector":"データセンタ・GPUクラウド","surge":1.445,"z":0.07,"recent":215648200,"share_recent":0.031,"share_base":0.029,"share_delta":0.002,"last":2891.0,"pct":-2.43},{"code":"7912.T","name":"大日本印刷","bucket":"leader","sector":"その他製品","surge":1.443,"z":0.93,"recent":396219000,"share_recent":0.058,"share_base":0.029,"share_delta":0.029,"last":3147.0,"pct":3.62},{"code":"8252.T","name":"丸井グループ","bucket":"leader","sector":"小売業","surge":1.433,"z":0.57,"recent":193748500,"share_recent":0.028,"share_base":0.015,"share_delta":0.013,"last":2952.0,"pct":1.08},{"code":"6471.T","name":"日本精工","bucket":"leader","sector":"機械","surge":1.432,"z":0.4,"recent":185333050,"share_recent":0.027,"share_base":0.014,"share_delta":0.013,"last":1141.5,"pct":-1.93},{"code":"4665.T","name":"ダスキン","bucket":"core","sector":"サービス業","surge":1.432,"z":0.27,"recent":30381600,"share_recent":0.004,"share_base":0.002,"share_delta":0.002,"last":4465.0,"pct":1.04},{"code":"9201.T","name":"日本航空","bucket":"leader","sector":"空運業","surge":1.43,"z":0.36,"recent":647829650,"share_recent":0.095,"share_base":0.053,"share_delta":0.042,"last":2980.0,"pct":-2.93},{"code":"3402.T","name":"東レ","bucket":"leader","sector":"繊維製品","surge":1.429,"z":0.21,"recent":387801200,"share_recent":0.057,"share_base":0.032,"share_delta":0.024,"last":1147.5,"pct":0.0},{"code":"7458.T","name":"第一興商","bucket":"core","sector":"卸売業","surge":1.427,"z":0.04,"recent":29770450,"share_recent":0.004,"share_base":0.003,"share_delta":0.002,"last":1750.0,"pct":0.72},{"code":"9505.T","name":"北陸電力","bucket":"core","sector":"電気・ガス業","surge":1.427,"z":0.16,"recent":49694830,"share_recent":0.007,"share_base":0.004,"share_delta":0.003,"last":911.0,"pct":2.45},{"code":"7164.T","name":"全国保証","bucket":"core","sector":"その他金融業","surge":1.426,"z":0.15,"recent":109117800,"share_recent":0.016,"share_base":0.01,"share_delta":0.006,"last":3097.0,"pct":0.06},{"code":"9104.T","name":"商船三井","bucket":"leader","sector":"海運業","surge":1.424,"z":0.15,"recent":938847900,"share_recent":0.137,"share_base":0.082,"share_delta":0.055,"last":5469.0,"pct":4.51},{"code":"4188.T","name":"三菱ケミカルグループ","bucket":"leader","sector":"化学","surge":1.421,"z":0.41,"recent":501047700,"share_recent":0.073,"share_base":0.039,"share_delta":0.034,"last":1164.0,"pct":2.46},{"code":"2282.T","name":"日本ハム","bucket":"leader","sector":"食料品","surge":1.416,"z":0.64,"recent":227497000,"share_recent":0.033,"share_base":0.017,"share_delta":0.016,"last":6233.0,"pct":0.78},{"code":"4751.T","name":"サイバーエージェント","bucket":"leader","sector":"サービス業","surge":1.415,"z":0.12,"recent":565055350,"share_recent":0.083,"share_base":0.05,"share_delta":0.032,"last":1490.0,"pct":0.27},{"code":"9008.T","name":"京王電鉄","bucket":"leader","sector":"陸運業","surge":1.414,"z":0.68,"recent":111619830,"share_recent":0.016,"share_base":0.008,"share_delta":0.008,"last":751.2999877929688,"pct":0.24},{"code":"5332.T","name":"ＴＯＴＯ","bucket":"leader","sector":"ガラス・土石製品","surge":1.411,"z":0.43,"recent":694797000,"share_recent":0.101,"share_base":0.056,"share_delta":0.046,"last":8104.0,"pct":-3.75},{"code":"5201.T","name":"ＡＧＣ","bucket":"leader","sector":"ガラス・土石製品","surge":1.409,"z":0.76,"recent":642128000,"share_recent":0.094,"share_base":0.047,"share_delta":0.047,"last":6446.0,"pct":-4.86},{"code":"6988.T","name":"日東電工","bucket":"leader","sector":"化学","surge":1.405,"z":0.77,"recent":545191400,"share_recent":0.08,"share_base":0.04,"share_delta":0.04,"last":3135.0,"pct":-4.3},{"code":"8804.T","name":"東京建物","bucket":"leader","sector":"不動産業","surge":1.405,"z":0.2,"recent":279191700,"share_recent":0.041,"share_base":0.024,"share_delta":0.016,"last":3349.0,"pct":0.48},{"code":"7261.T","name":"マツダ","bucket":"leader","sector":"輸送用機器","surge":1.396,"z":0.26,"recent":635200400,"share_recent":0.093,"share_base":0.053,"share_delta":0.04,"last":1104.0,"pct":-1.56},{"code":"5938.T","name":"ＬＩＸＩＬ","bucket":"core","sector":"金属製品","surge":1.394,"z":0.16,"recent":339655350,"share_recent":0.05,"share_base":0.03,"share_delta":0.02,"last":1859.5,"pct":0.84},{"code":"8308.T","name":"りそなホールディングス","bucket":"leader","sector":"銀行業","surge":1.392,"z":0.25,"recent":1723834650,"share_recent":0.252,"share_base":0.143,"share_delta":0.109,"last":2352.5,"pct":6.26},{"code":"8801.T","name":"三井不動産","bucket":"leader","sector":"不動産業","surge":1.39,"z":0.64,"recent":823724100,"share_recent":0.12,"share_base":0.063,"share_delta":0.058,"last":1519.0,"pct":-2.72},{"code":"4568.T","name":"第一三共","bucket":"leader","sector":"医薬品","surge":1.387,"z":-0.14,"recent":1359839450,"share_recent":0.199,"share_base":0.149,"share_delta":0.05,"last":2714.5,"pct":1.16},{"code":"5108.T","name":"ブリヂストン","bucket":"leader","sector":"ゴム製品","surge":1.386,"z":0.38,"recent":847107800,"share_recent":0.124,"share_base":0.069,"share_delta":0.055,"last":3558.0,"pct":0.94},{"code":"9364.T","name":"上組","bucket":"core","sector":"倉庫・運輸関連業","surge":1.384,"z":-0.07,"recent":140400800,"share_recent":0.021,"share_base":0.014,"share_delta":0.006,"last":5275.0,"pct":0.73},{"code":"3099.T","name":"三越伊勢丹ホールディングス","bucket":"leader","sector":"小売業","surge":1.382,"z":0.63,"recent":731889800,"share_recent":0.107,"share_base":0.055,"share_delta":0.052,"last":3828.0,"pct":-3.72},{"code":"6005.T","name":"三浦工業","bucket":"core","sector":"機械","surge":1.382,"z":0.08,"recent":79941700,"share_recent":0.012,"share_base":0.007,"share_delta":0.005,"last":3184.0,"pct":0.76},{"code":"7201.T","name":"日産自動車","bucket":"leader","sector":"輸送用機器","surge":1.38,"z":0.18,"recent":742228912,"share_recent":0.108,"share_base":0.065,"share_delta":0.043,"last":304.5,"pct":-3.46},{"code":"9107.T","name":"川崎汽船","bucket":"leader","sector":"海運業","surge":1.379,"z":-0.04,"recent":816430300,"share_recent":0.119,"share_base":0.083,"share_delta":0.036,"last":2582.5,"pct":1.89},{"code":"1944.T","name":"きんでん","bucket":"core","sector":"建設業","surge":1.378,"z":0.11,"recent":323905300,"share_recent":0.047,"share_base":0.029,"share_delta":0.018,"last":7684.0,"pct":-3.0},{"code":"3401.T","name":"帝人","bucket":"leader","sector":"繊維製品","surge":1.377,"z":0.2,"recent":114764550,"share_recent":0.017,"share_base":0.01,"share_delta":0.007,"last":1682.5,"pct":1.17},{"code":"2222.T","name":"寿スピリッツ","bucket":"core","sector":"食料品","surge":1.374,"z":0.08,"recent":77821500,"share_recent":0.011,"share_base":0.007,"share_delta":0.004,"last":2547.5,"pct":1.31},{"code":"7956.T","name":"ピジョン","bucket":"core","sector":"その他製品","surge":1.373,"z":0.29,"recent":123190600,"share_recent":0.018,"share_base":0.01,"share_delta":0.008,"last":2070.0,"pct":-1.83},{"code":"2002.T","name":"日清製粉グループ本社","bucket":"leader","sector":"食料品","surge":1.372,"z":0.28,"recent":85289050,"share_recent":0.012,"share_base":0.007,"share_delta":0.005,"last":2039.0,"pct":1.39},{"code":"3003.T","name":"ヒューリック","bucket":"core","sector":"不動産業","surge":1.372,"z":0.58,"recent":288303600,"share_recent":0.042,"share_base":0.022,"share_delta":0.02,"last":1752.0,"pct":0.31},{"code":"9404.T","name":"日本テレビホールディングス","bucket":"core","sector":"情報・通信業","surge":1.371,"z":0.12,"recent":89313000,"share_recent":0.013,"share_base":0.008,"share_delta":0.005,"last":2912.0,"pct":-0.43},{"code":"8233.T","name":"高島屋","bucket":"leader","sector":"小売業","surge":1.367,"z":0.75,"recent":425126300,"share_recent":0.062,"share_base":0.031,"share_delta":0.031,"last":2288.0,"pct":-5.0},{"code":"2811.T","name":"カゴメ","bucket":"core","sector":"食料品","surge":1.365,"z":0.03,"recent":46101050,"share_recent":0.007,"share_base":0.004,"share_delta":0.002,"last":2710.0,"pct":0.95},{"code":"7701.T","name":"島津製作所","bucket":"core","sector":"精密機器","surge":1.365,"z":0.45,"recent":208101200,"share_recent":0.03,"share_base":0.016,"share_delta":0.014,"last":3980.0,"pct":-3.56},{"code":"1719.T","name":"安藤・間","bucket":"core","sector":"建設業","surge":1.36,"z":0.06,"recent":71610250,"share_recent":0.01,"share_base":0.007,"share_delta":0.004,"last":1827.0,"pct":0.08},{"code":"2531.T","name":"宝ホールディングス","bucket":"core","sector":"食料品","surge":1.355,"z":0.07,"recent":90886700,"share_recent":0.013,"share_base":0.008,"share_delta":0.005,"last":2154.5,"pct":4.46},{"code":"2181.T","name":"パーソルホールディングス","bucket":"core","sector":"サービス業","surge":1.351,"z":0.37,"recent":89330591,"share_recent":0.013,"share_base":0.007,"share_delta":0.006,"last":256.20001220703125,"pct":0.04},{"code":"4118.T","name":"カネカ","bucket":"core","sector":"化学","surge":1.345,"z":0.11,"recent":86830200,"share_recent":0.013,"share_base":0.008,"share_delta":0.005,"last":5639.0,"pct":-0.07},{"code":"3563.T","name":"ＦＯＯＤ　＆　ＬＩＦＥ　ＣＯＭＰＡＮＩＥＳ","bucket":"core","sector":"小売業","surge":1.344,"z":0.47,"recent":954932700,"share_recent":0.139,"share_base":0.076,"share_delta":0.063,"last":4816.0,"pct":2.77},{"code":"2502.T","name":"アサヒグループホールディングス","bucket":"leader","sector":"食料品","surge":1.342,"z":-0.09,"recent":718020600,"share_recent":0.105,"share_base":0.078,"share_delta":0.027,"last":1629.0,"pct":3.43},{"code":"6368.T","name":"オルガノ","bucket":"core","sector":"機械","surge":1.337,"z":0.08,"recent":178962000,"share_recent":0.026,"share_base":0.016,"share_delta":0.01,"last":15365.0,"pct":-1.85},{"code":"2501.T","name":"サッポロホールディングス","bucket":"leader","sector":"食料品","surge":1.337,"z":0.13,"recent":206764900,"share_recent":0.03,"share_base":0.018,"share_delta":0.012,"last":2070.5,"pct":8.74},{"code":"6971.T","name":"京セラ","bucket":"leader","sector":"電気機器","surge":1.333,"z":0.21,"recent":1613164500,"share_recent":0.236,"share_base":0.138,"share_delta":0.098,"last":3709.0,"pct":-3.99},{"code":"5214.T","name":"日本電気硝子","bucket":"leader","sector":"ガラス・土石製品","surge":1.328,"z":0.37,"recent":316905500,"share_recent":0.046,"share_base":0.026,"share_delta":0.021,"last":5938.0,"pct":-4.52},{"code":"5105.T","name":"ＴＯＹＯ　ＴＩＲＥ","bucket":"core","sector":"ゴム製品","surge":1.328,"z":0.33,"recent":288322400,"share_recent":0.042,"share_base":0.024,"share_delta":0.018,"last":3883.0,"pct":0.41},{"code":"1414.T","name":"ショーボンドホールディングス","bucket":"core","sector":"建設業","surge":1.327,"z":0.47,"recent":53211200,"share_recent":0.008,"share_base":0.004,"share_delta":0.004,"last":1268.5,"pct":-0.47},{"code":"6361.T","name":"荏原製作所","bucket":"leader","sector":"機械","surge":1.327,"z":0.54,"recent":1715977400,"share_recent":0.251,"share_base":0.135,"share_delta":0.115,"last":5830.0,"pct":-0.1},{"code":"4183.T","name":"三井化学","bucket":"leader","sector":"化学","surge":1.326,"z":0.32,"recent":234420850,"share_recent":0.034,"share_base":0.019,"share_delta":0.015,"last":2095.5,"pct":-1.83},{"code":"6728.T","name":"アルバック","bucket":"core","sector":"電気機器","surge":1.322,"z":0.23,"recent":318995100,"share_recent":0.047,"share_base":0.027,"share_delta":0.019,"last":9311.0,"pct":-4.7},{"code":"9005.T","name":"東急","bucket":"leader","sector":"陸運業","surge":1.315,"z":0.13,"recent":250710950,"share_recent":0.037,"share_base":0.022,"share_delta":0.014,"last":1712.5,"pct":1.36},{"code":"6632.T","name":"ＪＶＣケンウッド","bucket":"core","sector":"電気機器","surge":1.313,"z":0.29,"recent":58514800,"share_recent":0.009,"share_base":0.005,"share_delta":0.004,"last":1098.5,"pct":-1.26},{"code":"9508.T","name":"九州電力","bucket":"core","sector":"電気・ガス業","surge":1.313,"z":0.15,"recent":198395650,"share_recent":0.029,"share_base":0.018,"share_delta":0.011,"last":1728.0,"pct":1.68},{"code":"3549.T","name":"クスリのアオキホールディングス","bucket":"core","sector":"小売業","surge":1.31,"z":0.22,"recent":84462500,"share_recent":0.012,"share_base":0.007,"share_delta":0.005,"last":3856.0,"pct":2.83},{"code":"6504.T","name":"富士電機","bucket":"leader","sector":"電気機器","surge":1.31,"z":0.06,"recent":726831000,"share_recent":0.106,"share_base":0.068,"share_delta":0.038,"last":12845.0,"pct":-2.39},{"code":"2433.T","name":"博報堂ＤＹホールディングス","bucket":"core","sector":"サービス業","surge":1.309,"z":0.2,"recent":63052600,"share_recent":0.009,"share_base":0.005,"share_delta":0.004,"last":1195.0,"pct":2.44},{"code":"3086.T","name":"Ｊ．フロントリテイリング","bucket":"leader","sector":"小売業","surge":1.307,"z":0.15,"recent":364419700,"share_recent":0.053,"share_base":0.032,"share_delta":0.021,"last":3239.0,"pct":-1.31},{"code":"4204.T","name":"積水化学工業","bucket":"core","sector":"化学","surge":1.307,"z":0.25,"recent":358730400,"share_recent":0.052,"share_base":0.031,"share_delta":0.021,"last":2614.0,"pct":-0.1},{"code":"5838.T","name":"楽天銀行","bucket":"core","sector":"銀行業","surge":1.301,"z":0.04,"recent":614693400,"share_recent":0.09,"share_base":0.058,"share_delta":0.032,"last":5718.0,"pct":6.58},{"code":"9503.T","name":"関西電力","bucket":"leader","sector":"電気・ガス業","surge":1.3,"z":0.12,"recent":476869950,"share_recent":0.07,"share_base":0.043,"share_delta":0.026,"last":2279.0,"pct":-0.98},{"code":"8012.T","name":"長瀬産業","bucket":"core","sector":"卸売業","surge":1.292,"z":0.13,"recent":46773750,"share_recent":0.007,"share_base":0.004,"share_delta":0.003,"last":1150.5,"pct":-2.66},{"code":"5333.T","name":"ＮＧＫ","bucket":"leader","sector":"ガラス・土石製品","surge":1.29,"z":0.13,"recent":921225000,"share_recent":0.135,"share_base":0.084,"share_delta":0.051,"last":7044.0,"pct":-2.14},{"code":"9989.T","name":"サンドラッグ","bucket":"core","sector":"小売業","surge":1.289,"z":0.31,"recent":106452400,"share_recent":0.016,"share_base":0.009,"share_delta":0.007,"last":3848.0,"pct":0.37},{"code":"8418.T","name":"山口フィナンシャルグループ","bucket":"core","sector":"銀行業","surge":1.284,"z":-0.01,"recent":98724500,"share_recent":0.014,"share_base":0.01,"share_delta":0.005,"last":3016.0,"pct":2.31},{"code":"8802.T","name":"三菱地所","bucket":"leader","sector":"不動産業","surge":1.282,"z":0.35,"recent":814393000,"share_recent":0.119,"share_base":0.068,"share_delta":0.051,"last":4194.0,"pct":-1.25},{"code":"1893.T","name":"五洋建設","bucket":"core","sector":"建設業","surge":1.281,"z":0.23,"recent":198364700,"share_recent":0.029,"share_base":0.017,"share_delta":0.012,"last":1638.0,"pct":-2.38},{"code":"8766.T","name":"東京海上ホールディングス","bucket":"leader","sector":"損害保険","surge":1.281,"z":0.06,"recent":2958792200,"share_recent":0.432,"share_base":0.419,"share_delta":0.013,"last":7585.0,"pct":3.54},{"code":"6702.T","name":"富士通","bucket":"leader","sector":"電気機器","surge":1.278,"z":0.19,"recent":1196773900,"share_recent":0.175,"share_base":0.105,"share_delta":0.07,"last":3376.0,"pct":-1.34},{"code":"6861.T","name":"キーエンス","bucket":"leader","sector":"FA・センサー","surge":1.278,"z":0.13,"recent":2558968000,"share_recent":0.374,"share_base":0.346,"share_delta":0.028,"last":77300.0,"pct":-5.1},{"code":"5110.T","name":"住友ゴム工業","bucket":"core","sector":"ゴム製品","surge":1.277,"z":0.62,"recent":364748050,"share_recent":0.053,"share_base":0.028,"share_delta":0.025,"last":2180.0,"pct":-0.46},{"code":"8309.T","name":"三井住友トラストグループ","bucket":"leader","sector":"銀行業","surge":1.269,"z":0.09,"recent":1151019200,"share_recent":0.168,"share_base":0.106,"share_delta":0.062,"last":6559.0,"pct":3.41},{"code":"5301.T","name":"東海カーボン","bucket":"leader","sector":"ガラス・土石製品","surge":1.269,"z":0.54,"recent":200758300,"share_recent":0.029,"share_base":0.016,"share_delta":0.014,"last":1670.5,"pct":-3.05},{"code":"7270.T","name":"ＳＵＢＡＲＵ","bucket":"leader","sector":"輸送用機器","surge":1.266,"z":0.05,"recent":545590150,"share_recent":0.08,"share_base":0.051,"share_delta":0.028,"last":2481.0,"pct":-1.82},{"code":"6770.T","name":"アルプスアルパイン","bucket":"leader","sector":"電気機器","surge":1.261,"z":0.39,"recent":236892050,"share_recent":0.035,"share_base":0.019,"share_delta":0.016,"last":2054.0,"pct":-2.45},{"code":"5706.T","name":"三井金属","bucket":"leader","sector":"非鉄金属","surge":1.258,"z":0.25,"recent":4610817000,"share_recent":0.673,"share_base":0.394,"share_delta":0.28,"last":35020.0,"pct":-5.86},{"code":"6674.T","name":"ジーエス・ユアサ　コーポレーション","bucket":"core","sector":"電気機器","surge":1.258,"z":0.48,"recent":392366300,"share_recent":0.057,"share_base":0.032,"share_delta":0.025,"last":6187.0,"pct":-5.18},{"code":"6305.T","name":"日立建機","bucket":"leader","sector":"機械","surge":1.253,"z":0.25,"recent":255114800,"share_recent":0.037,"share_base":0.022,"share_delta":0.015,"last":5245.0,"pct":-0.29},{"code":"4205.T","name":"日本ゼオン","bucket":"core","sector":"化学","surge":1.253,"z":0.29,"recent":163295450,"share_recent":0.024,"share_base":0.014,"share_delta":0.01,"last":2290.0,"pct":0.0},{"code":"9507.T","name":"四国電力","bucket":"core","sector":"電気・ガス業","surge":1.248,"z":0.33,"recent":40474600,"share_recent":0.006,"share_base":0.003,"share_delta":0.003,"last":1493.0,"pct":0.2},{"code":"6925.T","name":"ウシオ電機","bucket":"core","sector":"電気機器","surge":1.246,"z":0.23,"recent":154523300,"share_recent":0.023,"share_base":0.014,"share_delta":0.009,"last":4285.0,"pct":-4.37},{"code":"4887.T","name":"サワイグループホールディングス","bucket":"core","sector":"医薬品","surge":1.243,"z":0.24,"recent":36837900,"share_recent":0.005,"share_base":0.003,"share_delta":0.002,"last":1688.5,"pct":-2.29},{"code":"8088.T","name":"岩谷産業","bucket":"core","sector":"卸売業","surge":1.242,"z":0.17,"recent":135606750,"share_recent":0.02,"share_base":0.012,"share_delta":0.008,"last":1976.5,"pct":0.05},{"code":"4045.T","name":"東亞合成","bucket":"core","sector":"化学","surge":1.241,"z":-0.1,"recent":31170550,"share_recent":0.005,"share_base":0.003,"share_delta":0.001,"last":1738.0,"pct":-1.14},{"code":"6754.T","name":"アンリツ","bucket":"core","sector":"電気機器","surge":1.24,"z":-0.05,"recent":465131000,"share_recent":0.068,"share_base":0.048,"share_delta":0.02,"last":4078.0,"pct":-5.6},{"code":"8136.T","name":"サンリオ","bucket":"core","sector":"卸売業","surge":1.24,"z":0.04,"recent":2090440800,"share_recent":0.305,"share_base":0.198,"share_delta":0.108,"last":1129.5,"pct":4.83},{"code":"5406.T","name":"神戸製鋼所","bucket":"leader","sector":"鉄鋼","surge":1.239,"z":0.27,"recent":276122250,"share_recent":0.04,"share_base":0.024,"share_delta":0.017,"last":1874.5,"pct":-1.03},{"code":"1925.T","name":"大和ハウス工業","bucket":"leader","sector":"建設業","surge":1.225,"z":0.27,"recent":511901700,"share_recent":0.075,"share_base":0.044,"share_delta":0.031,"last":4537.0,"pct":-0.29},{"code":"1878.T","name":"大東建託","bucket":"core","sector":"不動産業","surge":1.223,"z":-0.0,"recent":266300600,"share_recent":0.039,"share_base":0.026,"share_delta":0.013,"last":3171.0,"pct":-0.81},{"code":"7182.T","name":"ゆうちょ銀行","bucket":"core","sector":"銀行業","surge":1.221,"z":0.02,"recent":1103721400,"share_recent":0.161,"share_base":0.106,"share_delta":0.055,"last":3280.0,"pct":3.18},{"code":"4543.T","name":"テルモ","bucket":"leader","sector":"精密機器","surge":1.22,"z":0.19,"recent":521996200,"share_recent":0.076,"share_base":0.046,"share_delta":0.03,"last":2216.5,"pct":-4.71},{"code":"4755.T","name":"楽天グループ","bucket":"leader","sector":"サービス業","surge":1.219,"z":0.05,"recent":919841729,"share_recent":0.134,"share_base":0.086,"share_delta":0.048,"last":808.0,"pct":7.5},{"code":"9001.T","name":"東武鉄道","bucket":"leader","sector":"陸運業","surge":1.213,"z":-0.01,"recent":82663200,"share_recent":0.012,"share_base":0.008,"share_delta":0.004,"last":2908.5,"pct":-0.09},{"code":"8267.T","name":"イオン","bucket":"leader","sector":"小売業","surge":1.213,"z":-0.08,"recent":849939150,"share_recent":0.124,"share_base":0.087,"share_delta":0.038,"last":1413.0,"pct":-0.81},{"code":"9934.T","name":"因幡電機産業","bucket":"core","sector":"卸売業","surge":1.205,"z":0.1,"recent":28078850,"share_recent":0.004,"share_base":0.002,"share_delta":0.002,"last":2694.0,"pct":-2.16},{"code":"2768.T","name":"双日","bucket":"leader","sector":"卸売業","surge":1.202,"z":-0.09,"recent":371503600,"share_recent":0.054,"share_base":0.038,"share_delta":0.016,"last":5133.0,"pct":-3.15},{"code":"8410.T","name":"セブン銀行","bucket":"core","sector":"銀行業","surge":1.19,"z":0.08,"recent":86585100,"share_recent":0.013,"share_base":0.008,"share_delta":0.005,"last":292.20001220703125,"pct":0.93},{"code":"543A.T","name":"ＡＲＣＨＩＯＮ","bucket":"leader","sector":"輸送用機器","surge":1.188,"z":-0.13,"recent":89687400,"share_recent":0.013,"share_base":0.01,"share_delta":0.003,"last":301.0,"pct":-0.66},{"code":"9045.T","name":"京阪ホールディングス","bucket":"core","sector":"陸運業","surge":1.182,"z":0.17,"recent":47584300,"share_recent":0.007,"share_base":0.004,"share_delta":0.003,"last":3214.0,"pct":1.29},{"code":"6460.T","name":"セガサミーホールディングス","bucket":"core","sector":"機械","surge":1.177,"z":0.15,"recent":114645500,"share_recent":0.017,"share_base":0.01,"share_delta":0.006,"last":2404.0,"pct":2.63},{"code":"2801.T","name":"キッコーマン","bucket":"leader","sector":"食料品","surge":1.168,"z":-0.16,"recent":255437000,"share_recent":0.037,"share_base":0.028,"share_delta":0.009,"last":1662.0,"pct":0.09},{"code":"5991.T","name":"日本発條","bucket":"core","sector":"金属製品","surge":1.166,"z":0.02,"recent":235482900,"share_recent":0.034,"share_base":0.023,"share_delta":0.012,"last":3769.0,"pct":-2.58},{"code":"9984.T","name":"ソフトバンクグループ","bucket":"leader","sector":"投資持株・通信","surge":1.164,"z":-0.09,"recent":22408911900,"share_recent":3.273,"share_base":3.474,"share_delta":-0.202,"last":6416.0,"pct":4.67},{"code":"9987.T","name":"スズケン","bucket":"core","sector":"卸売業","surge":1.161,"z":-0.05,"recent":65383600,"share_recent":0.01,"share_base":0.006,"share_delta":0.003,"last":5023.0,"pct":0.2},{"code":"5803.T","name":"フジクラ","bucket":"hot","sector":"電線・光ファイバ(DC)","surge":1.156,"z":0.04,"recent":17222858600,"share_recent":2.515,"share_base":2.473,"share_delta":0.042,"last":5270.0,"pct":-15.9},{"code":"5411.T","name":"ＪＦＥホールディングス","bucket":"leader","sector":"鉄鋼","surge":1.154,"z":-0.08,"recent":541173950,"share_recent":0.079,"share_base":0.055,"share_delta":0.024,"last":1620.0,"pct":0.93},{"code":"4578.T","name":"大塚ホールディングス","bucket":"leader","sector":"医薬品","surge":1.154,"z":0.1,"recent":746396000,"share_recent":0.109,"share_base":0.069,"share_delta":0.04,"last":11015.0,"pct":-4.38},{"code":"5830.T","name":"いよぎんホールディングス","bucket":"core","sector":"銀行業","surge":1.154,"z":0.06,"recent":160160500,"share_recent":0.023,"share_base":0.015,"share_delta":0.008,"last":3287.0,"pct":-0.3},{"code":"6098.T","name":"リクルートホールディングス","bucket":"leader","sector":"人材・HRテック","surge":1.153,"z":-0.09,"recent":2753182000,"share_recent":0.402,"share_base":0.43,"share_delta":-0.028,"last":12255.0,"pct":3.86},{"code":"1951.T","name":"エクシオグループ","bucket":"core","sector":"建設業","surge":1.147,"z":0.17,"recent":111499600,"share_recent":0.016,"share_base":0.01,"share_delta":0.006,"last":2666.0,"pct":-2.74},{"code":"7747.T","name":"朝日インテック","bucket":"core","sector":"精密機器","surge":1.139,"z":0.09,"recent":229102700,"share_recent":0.033,"share_base":0.021,"share_delta":0.012,"last":3654.0,"pct":-4.67},{"code":"2127.T","name":"日本Ｍ＆Ａセンターホールディングス","bucket":"core","sector":"サービス業","surge":1.138,"z":-0.09,"recent":70704951,"share_recent":0.01,"share_base":0.007,"share_delta":0.003,"last":677.7000122070312,"pct":3.5},{"code":"8359.T","name":"八十二長野銀行","bucket":"core","sector":"銀行業","surge":1.126,"z":0.05,"recent":164915700,"share_recent":0.024,"share_base":0.016,"share_delta":0.008,"last":2572.5,"pct":3.48},{"code":"8795.T","name":"Ｔ＆Ｄホールディングス","bucket":"leader","sector":"保険業","surge":1.125,"z":0.12,"recent":604240200,"share_recent":0.088,"share_base":0.056,"share_delta":0.033,"last":4940.0,"pct":0.04},{"code":"8242.T","name":"エイチ・ツー・オー　リテイリング","bucket":"core","sector":"小売業","surge":1.125,"z":-0.11,"recent":76458750,"share_recent":0.011,"share_base":0.008,"share_delta":0.003,"last":2828.5,"pct":-2.95},{"code":"4403.T","name":"日油","bucket":"core","sector":"化学","surge":1.119,"z":0.03,"recent":125776800,"share_recent":0.018,"share_base":0.012,"share_delta":0.006,"last":2775.0,"pct":0.73},{"code":"7012.T","name":"川崎重工業","bucket":"leader","sector":"輸送用機器","surge":1.116,"z":-0.13,"recent":2560509000,"share_recent":0.374,"share_base":0.274,"share_delta":0.1,"last":2747.5,"pct":-2.62},{"code":"9142.T","name":"九州旅客鉄道","bucket":"core","sector":"陸運業","surge":1.111,"z":0.1,"recent":134124200,"share_recent":0.02,"share_base":0.012,"share_delta":0.007,"last":3573.0,"pct":0.7},{"code":"285A.T","name":"キオクシアホールディングス","bucket":"hot","sector":"半導体メモリ(NAND)","surge":1.104,"z":-0.12,"recent":281767191000,"share_recent":41.149,"share_base":43.321,"share_delta":-2.172,"last":80650.0,"pct":-11.68},{"code":"5401.T","name":"日本製鉄","bucket":"leader","sector":"鉄鋼","surge":1.103,"z":-0.01,"recent":831251897,"share_recent":0.121,"share_base":0.081,"share_delta":0.04,"last":554.4000244140625,"pct":0.53},{"code":"4385.T","name":"メルカリ","bucket":"leader","sector":"情報・通信業","surge":1.102,"z":-0.1,"recent":568096800,"share_recent":0.083,"share_base":0.059,"share_delta":0.024,"last":4616.0,"pct":7.8},{"code":"9064.T","name":"ヤマトホールディングス","bucket":"leader","sector":"陸運業","surge":1.101,"z":-0.01,"recent":155153150,"share_recent":0.023,"share_base":0.015,"share_delta":0.007,"last":1949.5,"pct":0.88},{"code":"6707.T","name":"サンケン電気","bucket":"core","sector":"電気機器","surge":1.099,"z":-0.05,"recent":109125500,"share_recent":0.016,"share_base":0.011,"share_delta":0.005,"last":10215.0,"pct":-5.55},{"code":"4587.T","name":"ペプチドリーム","bucket":"core","sector":"医薬品","surge":1.097,"z":-0.2,"recent":49278350,"share_recent":0.007,"share_base":0.005,"share_delta":0.002,"last":1021.5,"pct":-3.54},{"code":"7181.T","name":"かんぽ生命保険","bucket":"core","sector":"保険業","surge":1.096,"z":-0.08,"recent":179845850,"share_recent":0.026,"share_base":0.018,"share_delta":0.008,"last":1638.0,"pct":1.42},{"code":"5471.T","name":"大同特殊鋼","bucket":"core","sector":"鉄鋼","surge":1.095,"z":-0.05,"recent":176393850,"share_recent":0.026,"share_base":0.018,"share_delta":0.008,"last":2547.5,"pct":-8.36},{"code":"5713.T","name":"住友金属鉱山","bucket":"leader","sector":"非鉄金属","surge":1.093,"z":0.07,"recent":1715747400,"share_recent":0.251,"share_base":0.161,"share_delta":0.09,"last":7180.0,"pct":-8.58},{"code":"7272.T","name":"ヤマハ発動機","bucket":"leader","sector":"輸送用機器","surge":1.091,"z":-0.03,"recent":404126500,"share_recent":0.059,"share_base":0.04,"share_delta":0.019,"last":1231.5,"pct":-0.97},{"code":"6503.T","name":"三菱電機","bucket":"leader","sector":"電気機器","surge":1.088,"z":-0.12,"recent":1579349800,"share_recent":0.231,"share_base":0.164,"share_delta":0.066,"last":5770.0,"pct":-2.22},{"code":"2201.T","name":"森永製菓","bucket":"core","sector":"食料品","surge":1.086,"z":-0.24,"recent":43117000,"share_recent":0.006,"share_base":0.006,"share_delta":0.0,"last":2710.5,"pct":0.82},{"code":"4005.T","name":"住友化学","bucket":"leader","sector":"化学","surge":1.083,"z":-0.29,"recent":354910116,"share_recent":0.052,"share_base":0.043,"share_delta":0.009,"last":537.5,"pct":-3.05},{"code":"3861.T","name":"王子ホールディングス","bucket":"leader","sector":"パルプ・紙","surge":1.082,"z":-0.14,"recent":145418810,"share_recent":0.021,"share_base":0.015,"share_delta":0.006,"last":822.2000122070312,"pct":-1.06},{"code":"8031.T","name":"三井物産","bucket":"leader","sector":"総合商社","surge":1.079,"z":-0.27,"recent":1684696400,"share_recent":0.246,"share_base":0.295,"share_delta":-0.049,"last":4553.0,"pct":2.2},{"code":"4151.T","name":"協和キリン","bucket":"leader","sector":"医薬品","surge":1.078,"z":-0.05,"recent":172605550,"share_recent":0.025,"share_base":0.017,"share_delta":0.008,"last":2659.5,"pct":-0.23},{"code":"9302.T","name":"三井倉庫ホールディングス","bucket":"core","sector":"倉庫・運輸関連業","surge":1.076,"z":0.11,"recent":42435200,"share_recent":0.006,"share_base":0.004,"share_delta":0.002,"last":3472.0,"pct":-3.04},{"code":"5831.T","name":"しずおかフィナンシャルグループ","bucket":"leader","sector":"銀行業","surge":1.075,"z":-0.11,"recent":418682100,"share_recent":0.061,"share_base":0.043,"share_delta":0.018,"last":3307.0,"pct":4.85},{"code":"6592.T","name":"マブチモーター","bucket":"core","sector":"電気機器","surge":1.073,"z":-0.04,"recent":95830250,"share_recent":0.014,"share_base":0.009,"share_delta":0.005,"last":1612.0,"pct":1.35},{"code":"3349.T","name":"コスモス薬品","bucket":"core","sector":"小売業","surge":1.073,"z":0.0,"recent":158841700,"share_recent":0.023,"share_base":0.015,"share_delta":0.008,"last":6503.0,"pct":-0.66},{"code":"7988.T","name":"ニフコ","bucket":"core","sector":"化学","surge":1.063,"z":-0.22,"recent":75865400,"share_recent":0.011,"share_base":0.008,"share_delta":0.003,"last":5014.0,"pct":0.28},{"code":"6806.T","name":"ヒロセ電機","bucket":"core","sector":"電気機器","surge":1.057,"z":-0.04,"recent":212319500,"share_recent":0.031,"share_base":0.021,"share_delta":0.01,"last":27610.0,"pct":-3.71},{"code":"9502.T","name":"中部電力","bucket":"leader","sector":"電気・ガス業","surge":1.055,"z":-0.08,"recent":790496800,"share_recent":0.115,"share_base":0.08,"share_delta":0.035,"last":3245.0,"pct":4.21},{"code":"3697.T","name":"ＳＨＩＦＴ","bucket":"leader","sector":"情報・通信業","surge":1.054,"z":-0.31,"recent":247681511,"share_recent":0.036,"share_base":0.03,"share_delta":0.006,"last":691.7999877929688,"pct":-3.5},{"code":"9009.T","name":"京成電鉄","bucket":"leader","sector":"陸運業","surge":1.05,"z":-0.29,"recent":122253500,"share_recent":0.018,"share_base":0.016,"share_delta":0.001,"last":1229.5,"pct":2.89},{"code":"8876.T","name":"リログループ","bucket":"core","sector":"サービス業","surge":1.049,"z":-0.06,"recent":113430350,"share_recent":0.017,"share_base":0.011,"share_delta":0.005,"last":2119.0,"pct":0.78},{"code":"3105.T","name":"日清紡ホールディングス","bucket":"core","sector":"電気機器","surge":1.043,"z":0.04,"recent":144045300,"share_recent":0.021,"share_base":0.014,"share_delta":0.007,"last":2285.0,"pct":-7.58},{"code":"8572.T","name":"アコム","bucket":"core","sector":"その他金融業","surge":1.04,"z":-0.11,"recent":43048510,"share_recent":0.006,"share_base":0.004,"share_delta":0.002,"last":482.1000061035156,"pct":2.62},{"code":"9504.T","name":"中国電力","bucket":"core","sector":"電気・ガス業","surge":1.038,"z":-0.1,"recent":94558450,"share_recent":0.014,"share_base":0.01,"share_delta":0.004,"last":928.0999755859375,"pct":-0.1},{"code":"6724.T","name":"セイコーエプソン","bucket":"leader","sector":"電気機器","surge":1.02,"z":-0.35,"recent":277657550,"share_recent":0.041,"share_base":0.036,"share_delta":0.004,"last":2776.0,"pct":1.55},{"code":"7337.T","name":"ひろぎんホールディングス","bucket":"core","sector":"銀行業","surge":1.02,"z":-0.25,"recent":71641450,"share_recent":0.01,"share_base":0.008,"share_delta":0.003,"last":2221.5,"pct":1.86},{"code":"6301.T","name":"コマツ","bucket":"leader","sector":"建設機械","surge":1.005,"z":-0.27,"recent":998812700,"share_recent":0.146,"share_base":0.177,"share_delta":-0.031,"last":6379.0,"pct":0.84},{"code":"2264.T","name":"森永乳業","bucket":"core","sector":"食料品","surge":1.005,"z":-0.04,"recent":138727100,"share_recent":0.02,"share_base":0.014,"share_delta":0.007,"last":1291.0,"pct":-3.19},{"code":"8473.T","name":"ＳＢＩホールディングス","bucket":"core","sector":"証券、商品先物取引業","surge":1.004,"z":-0.25,"recent":794247100,"share_recent":0.116,"share_base":0.095,"share_delta":0.021,"last":2698.5,"pct":-0.41},{"code":"8303.T","name":"ＳＢＩ新生銀行","bucket":"core","sector":"銀行業","surge":0.991,"z":-0.42,"recent":269048050,"share_recent":0.039,"share_base":0.038,"share_delta":0.001,"last":1438.5,"pct":-0.31},{"code":"8001.T","name":"伊藤忠商事","bucket":"leader","sector":"総合商社","surge":0.986,"z":-0.2,"recent":1272303250,"share_recent":0.186,"share_base":0.205,"share_delta":-0.019,"last":1879.5,"pct":1.51},{"code":"8334.T","name":"群馬銀行","bucket":"core","sector":"銀行業","surge":0.985,"z":-0.3,"recent":121792350,"share_recent":0.018,"share_base":0.013,"share_delta":0.004,"last":2478.0,"pct":2.29},{"code":"8253.T","name":"クレディセゾン","bucket":"leader","sector":"その他金融業","surge":0.984,"z":-0.21,"recent":155049500,"share_recent":0.023,"share_base":0.019,"share_delta":0.004,"last":4625.0,"pct":0.33},{"code":"6963.T","name":"ローム","bucket":"leader","sector":"電気機器","surge":0.98,"z":-0.29,"recent":2314734900,"share_recent":0.338,"share_base":0.271,"share_delta":0.067,"last":5583.0,"pct":5.34},{"code":"7202.T","name":"いすゞ自動車","bucket":"leader","sector":"輸送用機器","surge":0.97,"z":-0.29,"recent":396371850,"share_recent":0.058,"share_base":0.049,"share_delta":0.009,"last":2341.5,"pct":3.88},{"code":"4912.T","name":"ライオン","bucket":"core","sector":"化学","surge":0.967,"z":-0.23,"recent":105888800,"share_recent":0.015,"share_base":0.011,"share_delta":0.004,"last":1713.5,"pct":-1.83},{"code":"3405.T","name":"クラレ","bucket":"leader","sector":"化学","surge":0.966,"z":-0.2,"recent":133920150,"share_recent":0.02,"share_base":0.015,"share_delta":0.005,"last":1685.5,"pct":-1.29},{"code":"5832.T","name":"ちゅうぎんフィナンシャルグループ","bucket":"core","sector":"銀行業","surge":0.966,"z":-0.3,"recent":57267200,"share_recent":0.008,"share_base":0.007,"share_delta":0.001,"last":3235.0,"pct":1.57},{"code":"4506.T","name":"住友ファーマ","bucket":"leader","sector":"医薬品","surge":0.962,"z":-0.2,"recent":260560550,"share_recent":0.038,"share_base":0.029,"share_delta":0.009,"last":1436.5,"pct":-6.87},{"code":"6954.T","name":"ファナック","bucket":"leader","sector":"FA・産業用ロボット","surge":0.962,"z":-0.37,"recent":1775469800,"share_recent":0.259,"share_base":0.344,"share_delta":-0.085,"last":7220.0,"pct":-3.05},{"code":"8053.T","name":"住友商事","bucket":"leader","sector":"卸売業","surge":0.957,"z":-0.23,"recent":805101400,"share_recent":0.118,"share_base":0.09,"share_delta":0.028,"last":1563.5,"pct":-3.43},{"code":"2875.T","name":"東洋水産","bucket":"core","sector":"食料品","surge":0.955,"z":-0.28,"recent":220180500,"share_recent":0.032,"share_base":0.024,"share_delta":0.008,"last":10745.0,"pct":1.94},{"code":"8604.T","name":"野村ホールディングス","bucket":"leader","sector":"証券、商品先物取引業","surge":0.954,"z":-0.29,"recent":777526500,"share_recent":0.114,"share_base":0.093,"share_delta":0.02,"last":1520.5,"pct":3.51},{"code":"6965.T","name":"浜松ホトニクス","bucket":"core","sector":"電気機器","surge":0.951,"z":-0.29,"recent":529686000,"share_recent":0.077,"share_base":0.063,"share_delta":0.014,"last":2405.5,"pct":-6.94},{"code":"7729.T","name":"東京精密","bucket":"core","sector":"精密機器","surge":0.941,"z":-0.21,"recent":695652500,"share_recent":0.102,"share_base":0.077,"share_delta":0.025,"last":18070.0,"pct":-0.9},{"code":"5463.T","name":"丸一鋼管","bucket":"core","sector":"鉄鋼","surge":0.927,"z":-0.34,"recent":69217400,"share_recent":0.01,"share_base":0.009,"share_delta":0.001,"last":1799.5,"pct":-6.15},{"code":"7189.T","name":"西日本フィナンシャルホールディングス","bucket":"core","sector":"銀行業","surge":0.918,"z":-0.33,"recent":80987200,"share_recent":0.012,"share_base":0.01,"share_delta":0.002,"last":4309.0,"pct":1.6},{"code":"417A.T","name":"ブルーゾーンホールディングス","bucket":"core","sector":"小売業","surge":0.912,"z":-0.35,"recent":22573450,"share_recent":0.003,"share_base":0.003,"share_delta":0.001,"last":1775.0,"pct":0.17},{"code":"6981.T","name":"村田製作所","bucket":"leader","sector":"電子部品(MLCC)","surge":0.912,"z":-0.37,"recent":19114518400,"share_recent":2.791,"share_base":3.602,"share_delta":-0.811,"last":9984.0,"pct":-14.41},{"code":"2802.T","name":"味の素","bucket":"leader","sector":"食料品","surge":0.908,"z":-0.47,"recent":1137215500,"share_recent":0.166,"share_base":0.144,"share_delta":0.022,"last":5727.0,"pct":-5.68},{"code":"9434.T","name":"ソフトバンク","bucket":"leader","sector":"通信","surge":0.907,"z":-0.34,"recent":750253155,"share_recent":0.11,"share_base":0.129,"share_delta":-0.02,"last":211.8000030517578,"pct":2.62},{"code":"6383.T","name":"ダイフク","bucket":"core","sector":"機械","surge":0.898,"z":-0.36,"recent":463923800,"share_recent":0.068,"share_base":0.054,"share_delta":0.014,"last":6759.0,"pct":-3.83},{"code":"4208.T","name":"ＵＢＥ","bucket":"leader","sector":"化学","surge":0.897,"z":-0.43,"recent":125967400,"share_recent":0.018,"share_base":0.016,"share_delta":0.002,"last":3159.0,"pct":-1.62},{"code":"7180.T","name":"九州フィナンシャルグループ","bucket":"core","sector":"銀行業","surge":0.897,"z":-0.47,"recent":97825100,"share_recent":0.014,"share_base":0.013,"share_delta":0.001,"last":1527.0,"pct":2.17},{"code":"6268.T","name":"ナブテスコ","bucket":"core","sector":"機械","surge":0.893,"z":-0.41,"recent":358179500,"share_recent":0.052,"share_base":0.046,"share_delta":0.006,"last":5363.0,"pct":2.09},{"code":"1812.T","name":"鹿島建設","bucket":"leader","sector":"建設業","surge":0.89,"z":-0.33,"recent":532669100,"share_recent":0.078,"share_base":0.063,"share_delta":0.015,"last":5815.0,"pct":-5.92},{"code":"5016.T","name":"ＪＸ金属","bucket":"core","sector":"非鉄金属","surge":0.872,"z":-0.41,"recent":5738805200,"share_recent":0.838,"share_base":0.698,"share_delta":0.14,"last":3883.0,"pct":-2.56},{"code":"9513.T","name":"電源開発","bucket":"core","sector":"電気・ガス業","surge":0.861,"z":-0.37,"recent":119501700,"share_recent":0.017,"share_base":0.014,"share_delta":0.003,"last":3629.0,"pct":-3.23},{"code":"8002.T","name":"丸紅","bucket":"leader","sector":"卸売業","surge":0.86,"z":-0.36,"recent":1194719900,"share_recent":0.174,"share_base":0.155,"share_delta":0.02,"last":4909.0,"pct":-0.71},{"code":"1803.T","name":"清水建設","bucket":"leader","sector":"建設業","surge":0.858,"z":-0.38,"recent":355824800,"share_recent":0.052,"share_base":0.044,"share_delta":0.008,"last":2487.0,"pct":-4.49},{"code":"9006.T","name":"京浜急行電鉄","bucket":"core","sector":"陸運業","surge":0.853,"z":-0.42,"recent":59924050,"share_recent":0.009,"share_base":0.008,"share_delta":0.001,"last":1547.5,"pct":1.91},{"code":"6526.T","name":"ソシオネクスト","bucket":"hot","sector":"半導体設計(SoC)","surge":0.832,"z":-0.52,"recent":1620851100,"share_recent":0.237,"share_base":0.374,"share_delta":-0.137,"last":2856.0,"pct":8.99},{"code":"2331.T","name":"ＡＬＳＯＫ","bucket":"core","sector":"サービス業","surge":0.828,"z":-0.51,"recent":54962550,"share_recent":0.008,"share_base":0.007,"share_delta":0.001,"last":1110.0,"pct":1.46},{"code":"6762.T","name":"ＴＤＫ","bucket":"leader","sector":"電気機器","surge":0.825,"z":-0.59,"recent":2272491200,"share_recent":0.332,"share_base":0.31,"share_delta":0.022,"last":3388.0,"pct":-7.51},{"code":"7203.T","name":"トヨタ自動車","bucket":"leader","sector":"自動車","surge":0.818,"z":-0.49,"recent":3122679500,"share_recent":0.456,"share_base":0.692,"share_delta":-0.236,"last":2831.0,"pct":2.37},{"code":"8306.T","name":"三菱UFJフィナンシャルG","bucket":"leader","sector":"銀行","surge":0.811,"z":-0.49,"recent":4268244600,"share_recent":0.623,"share_base":1.026,"share_delta":-0.402,"last":3446.0,"pct":5.58},{"code":"6525.T","name":"ＫＯＫＵＳＡＩ　ＥＬＥＣＴＲＩＣ","bucket":"core","sector":"電気機器","surge":0.808,"z":-0.54,"recent":6970499500,"share_recent":1.018,"share_base":0.939,"share_delta":0.079,"last":10805.0,"pct":8.15},{"code":"3436.T","name":"SUMCO","bucket":"hot","sector":"半導体シリコンウェハ","surge":0.807,"z":-0.53,"recent":6053565700,"share_recent":0.884,"share_base":1.346,"share_delta":-0.462,"last":5244.0,"pct":20.41},{"code":"4902.T","name":"コニカミノルタ","bucket":"leader","sector":"電気機器","surge":0.802,"z":-0.38,"recent":89209540,"share_recent":0.013,"share_base":0.012,"share_delta":0.001,"last":574.7999877929688,"pct":0.6},{"code":"9101.T","name":"日本郵船","bucket":"leader","sector":"海運","surge":0.787,"z":-0.48,"recent":557532600,"share_recent":0.081,"share_base":0.13,"share_delta":-0.049,"last":5276.0,"pct":1.58},{"code":"9432.T","name":"日本電信電話","bucket":"leader","sector":"通信","surge":0.781,"z":-0.65,"recent":1511900949,"share_recent":0.221,"share_base":0.339,"share_delta":-0.118,"last":147.89999389648438,"pct":3.07},{"code":"7003.T","name":"三井Ｅ＆Ｓ","bucket":"core","sector":"機械","surge":0.772,"z":-0.47,"recent":698355900,"share_recent":0.102,"share_base":0.117,"share_delta":-0.015,"last":4481.0,"pct":1.08},{"code":"6923.T","name":"スタンレー電気","bucket":"core","sector":"電気機器","surge":0.769,"z":-0.59,"recent":83717500,"share_recent":0.012,"share_base":0.011,"share_delta":0.001,"last":3505.0,"pct":-3.68},{"code":"4689.T","name":"ＬＩＮＥヤフー","bucket":"leader","sector":"情報・通信業","surge":0.768,"z":-0.6,"recent":233196529,"share_recent":0.034,"share_base":0.034,"share_delta":0.0,"last":444.3999938964844,"pct":-0.27},{"code":"6701.T","name":"日本電気","bucket":"leader","sector":"電気機器","surge":0.743,"z":-0.58,"recent":1285486200,"share_recent":0.188,"share_base":0.184,"share_delta":0.003,"last":4381.0,"pct":2.58},{"code":"7004.T","name":"カナデビア","bucket":"leader","sector":"機械","surge":0.738,"z":-0.68,"recent":52104400,"share_recent":0.008,"share_base":0.008,"share_delta":0.0,"last":1243.0,"pct":-4.97},{"code":"6976.T","name":"太陽誘電","bucket":"leader","sector":"電気機器","surge":0.724,"z":-0.73,"recent":22102539500,"share_recent":3.228,"share_base":3.253,"share_delta":-0.025,"last":14705.0,"pct":-21.49},{"code":"8316.T","name":"三井住友フィナンシャルG","bucket":"leader","sector":"銀行","surge":0.716,"z":-0.62,"recent":2568934300,"share_recent":0.375,"share_base":0.687,"share_delta":-0.312,"last":6839.0,"pct":5.98},{"code":"8341.T","name":"七十七銀行","bucket":"core","sector":"銀行業","surge":0.693,"z":-0.71,"recent":70782400,"share_recent":0.01,"share_base":0.011,"share_delta":-0.001,"last":3519.0,"pct":1.47},{"code":"8411.T","name":"みずほフィナンシャルG","bucket":"leader","sector":"銀行","surge":0.69,"z":-0.63,"recent":2134997900,"share_recent":0.312,"share_base":0.603,"share_delta":-0.292,"last":8337.0,"pct":5.33},{"code":"7751.T","name":"キヤノン","bucket":"leader","sector":"精密機器","surge":0.689,"z":-0.69,"recent":502704200,"share_recent":0.073,"share_base":0.121,"share_delta":-0.048,"last":4334.0,"pct":3.36},{"code":"7974.T","name":"任天堂","bucket":"leader","sector":"ゲーム","surge":0.689,"z":-0.64,"recent":2008363700,"share_recent":0.293,"share_base":0.524,"share_delta":-0.231,"last":7029.0,"pct":2.54},{"code":"6723.T","name":"ルネサスエレクトロニクス","bucket":"hot","sector":"半導体(車載マイコン)","surge":0.686,"z":-0.63,"recent":3240370900,"share_recent":0.473,"share_base":0.821,"share_delta":-0.347,"last":4902.0,"pct":-5.24},{"code":"5802.T","name":"住友電気工業","bucket":"leader","sector":"非鉄金属","surge":0.684,"z":-0.68,"recent":2493585850,"share_recent":0.364,"share_base":0.405,"share_delta":-0.041,"last":2389.0,"pct":-5.54},{"code":"4004.T","name":"レゾナック・ホールディングス","bucket":"leader","sector":"化学","surge":0.675,"z":-0.74,"recent":1777786500,"share_recent":0.26,"share_base":0.309,"share_delta":-0.049,"last":15725.0,"pct":-4.93},{"code":"7735.T","name":"ＳＣＲＥＥＮホールディングス","bucket":"leader","sector":"電気機器","surge":0.675,"z":-0.75,"recent":2822448500,"share_recent":0.412,"share_base":0.469,"share_delta":-0.057,"last":17775.0,"pct":2.16},{"code":"4980.T","name":"デクセリアルズ","bucket":"core","sector":"化学","surge":0.671,"z":-0.78,"recent":339839600,"share_recent":0.05,"share_base":0.054,"share_delta":-0.005,"last":4036.0,"pct":0.1},{"code":"7011.T","name":"三菱重工業","bucket":"hot","sector":"重工・防衛","surge":0.667,"z":-0.62,"recent":3116235100,"share_recent":0.455,"share_base":0.868,"share_delta":-0.413,"last":3843.0,"pct":1.91},{"code":"9509.T","name":"北海道電力","bucket":"core","sector":"電気・ガス業","surge":0.667,"z":-0.62,"recent":104671470,"share_recent":0.015,"share_base":0.017,"share_delta":-0.002,"last":972.9000244140625,"pct":2.84},{"code":"7936.T","name":"アシックス","bucket":"core","sector":"その他製品","surge":0.656,"z":-0.67,"recent":559150000,"share_recent":0.082,"share_base":0.092,"share_delta":-0.011,"last":4606.0,"pct":1.57},{"code":"4062.T","name":"イビデン","bucket":"leader","sector":"電気機器","surge":0.654,"z":-0.92,"recent":7767738500,"share_recent":1.134,"share_base":1.325,"share_delta":-0.191,"last":19550.0,"pct":-8.3},{"code":"6920.T","name":"レーザーテック","bucket":"hot","sector":"半導体検査装置(EUV)","surge":0.64,"z":-0.79,"recent":5226902000,"share_recent":0.763,"share_base":1.505,"share_delta":-0.742,"last":44910.0,"pct":-13.8},{"code":"9433.T","name":"KDDI","bucket":"leader","sector":"通信","surge":0.617,"z":-0.86,"recent":600069050,"share_recent":0.088,"share_base":0.165,"share_delta":-0.078,"last":2781.5,"pct":3.15},{"code":"6146.T","name":"ディスコ","bucket":"hot","sector":"半導体製造装置(ダイサ)","surge":0.611,"z":-0.83,"recent":4656091000,"share_recent":0.68,"share_base":1.361,"share_delta":-0.681,"last":73520.0,"pct":-15.03},{"code":"2914.T","name":"日本たばこ産業","bucket":"leader","sector":"たばこ","surge":0.602,"z":-0.73,"recent":832912900,"share_recent":0.122,"share_base":0.263,"share_delta":-0.142,"last":6127.0,"pct":1.91},{"code":"6752.T","name":"パナソニックホールディングス","bucket":"leader","sector":"電気機器","surge":0.601,"z":-0.76,"recent":1893915400,"share_recent":0.277,"share_base":0.395,"share_delta":-0.118,"last":4454.0,"pct":1.55},{"code":"7267.T","name":"ホンダ","bucket":"leader","sector":"自動車","surge":0.596,"z":-0.72,"recent":848450100,"share_recent":0.124,"share_base":0.274,"share_delta":-0.15,"last":1501.0,"pct":1.08},{"code":"6501.T","name":"日立製作所","bucket":"leader","sector":"総合電機","surge":0.579,"z":-0.71,"recent":1519737600,"share_recent":0.222,"share_base":0.495,"share_delta":-0.273,"last":4724.0,"pct":4.26},{"code":"8058.T","name":"三菱商事","bucket":"leader","sector":"総合商社","surge":0.568,"z":-0.88,"recent":1101323800,"share_recent":0.161,"share_base":0.326,"share_delta":-0.165,"last":4383.0,"pct":0.8},{"code":"4661.T","name":"オリエンタルランド","bucket":"leader","sector":"レジャー・テーマパーク","surge":0.567,"z":-1.01,"recent":371964900,"share_recent":0.054,"share_base":0.109,"share_delta":-0.055,"last":2605.5,"pct":5.57},{"code":"8304.T","name":"あおぞら銀行","bucket":"leader","sector":"銀行業","surge":0.567,"z":-0.79,"recent":163607400,"share_recent":0.024,"share_base":0.032,"share_delta":-0.008,"last":2900.5,"pct":2.64},{"code":"4063.T","name":"信越化学工業","bucket":"leader","sector":"半導体シリコンウェハ・化学","surge":0.555,"z":-0.85,"recent":1605488900,"share_recent":0.234,"share_base":0.524,"share_delta":-0.29,"last":7324.0,"pct":4.4},{"code":"5801.T","name":"古河電気工業","bucket":"hot","sector":"電線・光ファイバ","surge":0.55,"z":-0.9,"recent":3086782900,"share_recent":0.451,"share_base":0.955,"share_delta":-0.504,"last":3813.0,"pct":-18.42},{"code":"6857.T","name":"アドバンテスト","bucket":"hot","sector":"半導体検査装置(テスタ)","surge":0.548,"z":-0.87,"recent":8034706000,"share_recent":1.173,"share_base":2.684,"share_delta":-1.511,"last":30330.0,"pct":-9.84},{"code":"8035.T","name":"東京エレクトロン","bucket":"leader","sector":"半導体製造装置","surge":0.534,"z":-0.96,"recent":9577440000,"share_recent":1.399,"share_base":3.317,"share_delta":-1.919,"last":73900.0,"pct":-7.69},{"code":"4519.T","name":"中外製薬","bucket":"leader","sector":"医薬品","surge":0.482,"z":-1.0,"recent":417003600,"share_recent":0.061,"share_base":0.141,"share_delta":-0.08,"last":7373.0,"pct":-0.85},{"code":"5344.T","name":"ＭＡＲＵＷＡ","bucket":"core","sector":"ガラス・土石製品","surge":0.457,"z":-0.47,"recent":440812000,"share_recent":0.064,"share_base":0.123,"share_delta":-0.059,"last":60330.0,"pct":-12.27},{"code":"4502.T","name":"武田薬品工業","bucket":"leader","sector":"医薬品","surge":0.455,"z":-1.03,"recent":422352300,"share_recent":0.062,"share_base":0.155,"share_delta":-0.093,"last":5328.0,"pct":3.92},{"code":"7013.T","name":"IHI","bucket":"hot","sector":"重工・防衛(航空エンジン)","surge":0.453,"z":-0.88,"recent":1166083500,"share_recent":0.17,"share_base":0.47,"share_delta":-0.3,"last":2821.0,"pct":2.6},{"code":"6758.T","name":"ソニーグループ","bucket":"leader","sector":"電機・エンタメ","surge":0.37,"z":-1.0,"recent":1125773700,"share_recent":0.164,"share_base":0.504,"share_delta":-0.34,"last":3362.0,"pct":0.84},{"code":"7741.T","name":"HOYA","bucket":"leader","sector":"光学・半導体マスク","surge":0.353,"z":-1.3,"recent":518741500,"share_recent":0.076,"share_base":0.251,"share_delta":-0.175,"last":24975.0,"pct":-3.68},{"code":"6367.T","name":"ダイキン工業","bucket":"leader","sector":"空調","surge":0.34,"z":-0.99,"recent":569491500,"share_recent":0.083,"share_base":0.297,"share_delta":-0.213,"last":25195.0,"pct":1.78},{"code":"6902.T","name":"デンソー","bucket":"leader","sector":"自動車部品","surge":0.267,"z":-1.58,"recent":190569800,"share_recent":0.028,"share_base":0.11,"share_delta":-0.083,"last":1933.5,"pct":3.31}],"buckets":[{"bucket":"hot","label":"話題・噂","recent":335407286000,"n":12,"share":48.98},{"bucket":"leader","label":"けん引大型","recent":266650049909,"n":214,"share":38.94},{"bucket":"core","label":"主力","recent":82691056368,"n":271,"share":12.08}]}